{"1965": {"USA": {"x": 0.0, "m": 6089.618}, "ISR": {"m": 0.675}, "SWE": {"m": 61.326}, "DEU": {"x": 2.929, "m": 934.368}, "LKA": {"m": 45.685}, "IDN": {"m": 80.403}, "GBR": {"x": 6.585, "m": 9366.436}, "CAN": {"m": 363.254}, "KOR": {"m": 4.845}, "CHE": {"m": 70.56}, "CYP": {"m": 1.126}, "SER": {"m": 125.006}, "SGP": {"x": 500.458, "m": 4990.166}, "MYS": {"x": 62958.269, "m": 1701.983}, "PRT": {"m": 7.19}, "POL": {"m": 1.529}, "TTO": {"m": 1.261}, "KHM": {"m": 9.075}, "HKG": {"x": 6.505, "m": 1100.709}, "NLD": {"x": 2.041, "m": 864.526}, "SVR": {"m": 17.708}, "FRA": {"x": 0.0, "m": 377.393}, "UNS": {"x": 7.147, "m": 1043.251}, "BLX": {"x": 1.25, "m": 64.18}, "AUT": {"m": 42.892}, "ESP": {"m": 7.221}, "ZMB": {"m": 0.647}, "IRQ": {"m": 0.629}, "DNK": {"m": 227.641}, "PAK": {"m": 2.765}, "AUS": {"x": 54.044, "m": 1202.166}, "MMR": {"m": 3.285}, "CHN": {"m": 1595.819}, "IRN": {"x": 0.0}, "RUS": {"m": 14.431}, "FIN": {"x": 2.388, "m": 6.043}, "URY": {"m": 2.172}, "THA": {"m": 1235.194}, "NZL": {"m": 16.404}, "JPN": {"x": 0.0, "m": 3107.931}, "ZAF": {"m": 84.119}, "PHL": {"m": 9.098}, "ITA": {"m": 414.351}, "PNG": {"x": 0.0}, "ARG": {"m": 10.184}, "IND": {"m": 91.532}, "OAS": {"x": 0.0, "m": 383.403}, "BHR": {"m": 5.05}, "MEX": {"m": 2.069}, "NOR": {"x": 0.857, "m": 1.898}, "CZE": {"m": 81.046}}, "1962": {"TLS": {"m": 0.583}, "EGY": {"m": 2.449}, "USA": {"x": 0.0, "m": 919.191}, "SWE": {"m": 33.542}, "DEU": {"m": 244.372}, "LKA": {"m": 41.78}, "IDN": {"x": 0.0, "m": 77.903}, "GBR": {"x": 22.475, "m": 5271.98}, "CAN": {"m": 73.236}, "KOR": {"m": 0.594}, "SWK": {"x": 62454.541, "m": 441.553}, "CHE": {"m": 31.821}, "SPE": {"m": 1.438}, "PAK": {"x": 0.0, "m": 0.855}, "SGP": {"x": 903.234, "m": 2059.777}, "PMY": {"x": 0.0, "m": 268.528}, "NLD": {"x": 0.0, "m": 516.346}, "HKG": {"x": 68.362, "m": 870.091}, "SAU": {"x": 0.0, "m": 5.124}, "SVR": {"m": 10.853}, "FRA": {"x": 0.0, "m": 176.65}, "UNS": {"x": 6.106, "m": 669.717}, "BLX": {"m": 107.227}, "AUT": {"m": 10.834}, "ESP": {"m": 4.432}, "IRQ": {"m": 0.743}, "DNK": {"m": 133.973}, "AUS": {"x": 108.063, "m": 712.591}, "MMR": {"m": 16.237}, "CHN": {"m": 547.485}, "RUS": {"m": 17.956}, "FIN": {"m": 2.86}, "THA": {"m": 1085.816}, "NZL": {"x": 0.0, "m": 8.173}, "MAR": {"m": 4.388}, "JPN": {"m": 824.049}, "ZAF": {"m": 45.724}, "TUR": {"x": 0.0}, "PHL": {"m": 6.181}, "ITA": {"m": 51.798}, "ARG": {"m": 2.902}, "IND": {"x": 0.0, "m": 66.725}, "OAS": {"m": 257.798}, "SBH": {"x": 25.36, "m": 247.621}, "MEX": {"m": 0.757}, "NOR": {"m": 11.894}, "CZE": {"m": 3.243}}, "1963": {"EGY": {"m": 0.528}, "USA": {"x": 0.0, "m": 2110.904}, "SWE": {"m": 63.289}, "DEU": {"m": 557.337}, "LKA": {"m": 48.489}, "IDN": {"x": 0.0, "m": 81.434}, "GBR": {"x": 3.023, "m": 6048.58}, "CAN": {"m": 199.299}, "KOR": {"m": 1.863}, "SWK": {"x": 57707.695, "m": 473.623}, "CHE": {"m": 65.434}, "CYP": {"m": 1.036}, "SGP": {"x": 654.482, "m": 2671.615}, "HUN": {"m": 1.113}, "PMY": {"x": 0.0, "m": 402.538}, "PRT": {"m": 0.627}, "POL": {"m": 0.82}, "TTO": {"m": 1.57}, "NLD": {"x": 0.0, "m": 618.449}, "HKG": {"x": 29.595, "m": 1131.07}, "SAU": {"m": 2.458}, "SVR": {"m": 7.107}, "FRA": {"x": 0.0, "m": 176.684}, "UNS": {"x": 8.212, "m": 742.476}, "BLX": {"m": 88.547}, "AUT": {"m": 51.093}, "ESP": {"m": 4.378}, "MMR": {"m": 2.183}, "DNK": {"m": 185.927}, "PAK": {"m": 2.385}, "AUS": {"x": 72.102, "m": 793.192}, "JAM": {"m": 1.959}, "CHN": {"m": 885.005}, "RUS": {"m": 33.602}, "FIN": {"m": 5.754}, "THA": {"m": 1124.411}, "NZL": {"x": 0.0, "m": 9.688}, "MAR": {"m": 31.037}, "JPN": {"x": 3.084, "m": 1297.087}, "ZAF": {"x": 0.0, "m": 84.991}, "PHL": {"x": 0.0, "m": 5.301}, "ITA": {"m": 110.499}, "ARG": {"m": 7.815}, "IND": {"x": 0.0, "m": 68.351}, "OAS": {"m": 287.861}, "SBH": {"x": 14.745, "m": 226.074}, "MEX": {"m": 1.113}, "NOR": {"m": 1.162}, "CZE": {"m": 2.965}}, "1986": {"DZA": {"m": 0.846}, "FJI": {"m": 0.508}, "BGD": {"x": 0.0, "m": 0.878}, "USA": {"x": 106384.866, "m": 79795.144}, "DOM": {"m": 2.006}, "ISR": {"m": 11.771}, "GHA": {"m": 1.87}, "DEU": {"x": 0.0, "m": 39450.648}, "PER": {"m": 0.778}, "LKA": {"m": 60.948}, "IDN": {"x": 95.579, "m": 4259.705}, "GBR": {"x": 2.252, "m": 50509.324}, "CAN": {"m": 647.047}, "ISL": {"m": 2.667}, "KOR": {"x": 132225.374, "m": 5774.33}, "CHE": {"x": 0.0, "m": 2079.374}, "SLE": {"x": 0.0}, "JOR": {"x": 0.0, "m": 110.408}, "MYS": {"x": 1730.85, "m": 38351.196}, "ROM": {"m": 9.063}, "NRU": {"m": 0.858}, "HUN": {"m": 37.796}, "MDG": {"m": 1.96}, "TZA": {"m": 22.775}, "PRT": {"m": 51.24}, "POL": {"m": 3.037}, "NLD": {"x": 4.661, "m": 21792.15}, "HKG": {"x": 0.0, "m": 8544.267}, "LBN": {"m": 1.197}, "CUW": {"m": 0.578}, "VNM": {"m": 7.52}, "FRA": {"x": 0.0, "m": 10225.175}, "UNS": {"x": 3.445, "m": 785.578}, "SER": {"m": 25.125}, "BLX": {"m": 12769.795}, "AUT": {"m": 362.007}, "ESP": {"m": 332.559}, "IRQ": {"m": 3.543}, "SWE": {"x": 0.0, "m": 2325.887}, "CHL": {"m": 36.863}, "DNK": {"x": 0.0, "m": 4278.656}, "PAK": {"m": 121.175}, "NOR": {"x": 0.0, "m": 197.519}, "AUS": {"x": 14807.328, "m": 16700.078}, "MMR": {"m": 28.391}, "IRL": {"m": 79.494}, "CHN": {"m": 12321.906}, "IRN": {"m": 4.59}, "RUS": {"m": 9.737}, "PNG": {"x": 0.0, "m": 7.856}, "FIN": {"m": 107.811}, "URY": {"m": 31.557}, "THA": {"x": 145321.43, "m": 20312.808}, "NZL": {"x": 0.0, "m": 1797.645}, "NPL": {"m": 5.81}, "JPN": {"x": 1201350.756, "m": 115483.04}, "TUR": {"m": 17.547}, "PHL": {"x": 13147.879, "m": 1328.292}, "OMN": {"m": 0.564}, "ITA": {"x": 0.0, "m": 14661.737}, "SGP": {"x": 102157.936, "m": 168239.872}, "MAC": {"m": 36.426}, "ARE": {"m": 1.524}, "TUN": {"x": 0.0}, "ARG": {"m": 23.767}, "IND": {"x": 0.0, "m": 1450.37}, "OAS": {"x": 30143.078, "m": 15334.924}, "MNG": {"m": 3.015}, "MEX": {"m": 47.468}, "BRA": {"m": 677.691}, "CZE": {"m": 17.053}}, "1987": {"DZA": {"m": 1.93}, "EGY": {"x": 0.0, "m": 1.115}, "USA": {"x": 30155.147, "m": 77318.696}, "ISR": {"m": 9.764}, "SWE": {"x": 0.0, "m": 3054.567}, "DEU": {"x": 0.0, "m": 21822.062}, "LKA": {"x": 0.0, "m": 13.529}, "IDN": {"x": 52.231, "m": 5650.253}, "BGR": {"m": 17.666}, "GBR": {"x": 0.0, "m": 49960.756}, "CAN": {"x": 0.0, "m": 872.672}, "ISL": {"m": 22.886}, "KOR": {"x": 185338.208, "m": 9832.023}, "COL": {"m": 1.367}, "CHE": {"x": 0.0, "m": 1796.499}, "JOR": {"x": 0.0, "m": 126.451}, "CYP": {"m": 6.179}, "MYS": {"x": 1406.338, "m": 52647.84}, "SGP": {"x": 108574.504, "m": 154530.48}, "HUN": {"m": 40.467}, "MDG": {"m": 1.509}, "PRT": {"x": 0.0, "m": 77.792}, "POL": {"m": 5.37}, "NLD": {"x": 0.712, "m": 9977.52}, "CHN": {"m": 14612.165}, "HKG": {"x": 13.675, "m": 8459.019}, "SAU": {"x": 0.0, "m": 3.213}, "LBN": {"m": 11.984}, "CUW": {"m": 17.707}, "VNM": {"m": 19.617}, "FRA": {"x": 0.0, "m": 28981.892}, "UNS": {"x": 8.707, "m": 3631.041}, "SER": {"m": 14.761}, "BLX": {"x": 0.0, "m": 1162.17}, "ESP": {"m": 531.675}, "IRQ": {"m": 3.722}, "GRC": {"m": 8.146}, "CHL": {"m": 175.486}, "DNK": {"x": 0.0, "m": 3633.358}, "PAK": {"m": 120.204}, "ROM": {"m": 16.29}, "AUS": {"x": 19983.048, "m": 22326.448}, "MMR": {"m": 23.855}, "IRL": {"m": 22.794}, "AUT": {"m": 5072.972}, "IRN": {"m": 34.569}, "RUS": {"m": 18.819}, "FIN": {"m": 455.791}, "URY": {"m": 29.438}, "THA": {"x": 222281.684, "m": 27872.524}, "NZL": {"x": 0.0, "m": 2542.16}, "NPL": {"m": 7.479}, "JPN": {"x": 1174038.012, "m": 92200.952}, "TUR": {"m": 70.156}, "PHL": {"x": 61412.226, "m": 954.168}, "OMN": {"x": 0.0}, "ITA": {"x": 0.0, "m": 17111.356}, "MAC": {"m": 10.149}, "NOR": {"x": 0.0, "m": 169.231}, "ARG": {"m": 130.255}, "IND": {"x": 0.0, "m": 1296.614}, "OAS": {"x": 52162.734, "m": 16702.499}, "MNG": {"m": 4.41}, "MEX": {"m": 120.663}, "BRA": {"m": 1138.682}, "CZE": {"m": 14.865}}, "1984": {"QAT": {"x": 0.0}, "ROM": {"m": 2.622}, "GUF": {"m": 3.839}, "USA": {"x": 175585.95, "m": 94961.272}, "ISR": {"m": 13.085}, "USP": {"m": 58.235}, "SWE": {"x": 0.0, "m": 2356.177}, "DEU": {"x": 0.0, "m": 11694.125}, "LKA": {"x": 0.0, "m": 55.011}, "IDN": {"x": 0.0, "m": 1149.531}, "GBR": {"x": 0.0, "m": 51474.884}, "CAN": {"x": 0.0, "m": 810.806}, "ISL": {"m": 39.915}, "KOR": {"x": 173661.344, "m": 6078.808}, "CHE": {"x": 0.0, "m": 1470.189}, "CYP": {"m": 1.556}, "MYS": {"x": 2457.972, "m": 33742.008}, "SGP": {"x": 216416.292, "m": 151071.744}, "HUN": {"m": 13.844}, "MDG": {"m": 0.889}, "PRK": {"m": 11.331}, "PRT": {"x": 0.0, "m": 61.354}, "POL": {"m": 26.399}, "NLD": {"x": 4.306, "m": 16079.955}, "CHN": {"m": 12427.316}, "HKG": {"x": 0.0, "m": 9124.6}, "SAU": {"m": 114.629}, "MNG": {"m": 10.37}, "NPL": {"m": 8.006}, "VNM": {"m": 15.045}, "FRA": {"x": 72480.275, "m": 11237.73}, "UNS": {"x": 2.63, "m": 21279.498}, "SER": {"m": 31.214}, "BLX": {"m": 817.001}, "AUT": {"m": 317.391}, "ESP": {"m": 325.343}, "IRQ": {"m": 1.907}, "MMR": {"m": 43.411}, "AFG": {"m": 1.149}, "CHL": {"m": 4.61}, "DNK": {"x": 0.0, "m": 4129.407}, "PAK": {"x": 0.0, "m": 114.308}, "NOR": {"x": 0.0, "m": 189.777}, "AUS": {"x": 0.0, "m": 20517.044}, "MLT": {"m": 3.357}, "IRL": {"m": 2.052}, "GRC": {"m": 2.927}, "IRN": {"m": 182.42}, "RUS": {"m": 5.928}, "VEN": {"x": 0.0}, "PNG": {"m": 3.312}, "FIN": {"m": 39.724}, "THA": {"x": 207406.636, "m": 15864.206}, "NZL": {"x": 0.0, "m": 2453.156}, "KEN": {"m": 0.887}, "MAR": {"m": 3.238}, "JPN": {"x": 2187030.817, "m": 124699.488}, "ZAF": {"m": 7.438}, "TUR": {"m": 21.474}, "PHL": {"x": 54337.957, "m": 1148.541}, "ITA": {"m": 4923.776}, "MAC": {"m": 0.681}, "UGA": {"m": 1.546}, "ARE": {"m": 2.175}, "ARG": {"m": 31.498}, "IND": {"x": 0.0, "m": 1834.129}, "OAS": {"x": 68944.846, "m": 18389.048}, "BHS": {"m": 1.488}, "CZE": {"m": 13.266}, "MEX": {"m": 47.017}, "BRA": {"m": 245.784}, "CUB": {"m": 1.351}}, "1985": {"QAT": {"x": 0.0}, "USA": {"x": 217653.128, "m": 95661.528}, "ISR": {"m": 40.374}, "SWE": {"m": 2419.913}, "DEU": {"x": 0.0, "m": 23635.204}, "PER": {"x": 0.0}, "LKA": {"m": 35.202}, "IDN": {"x": 92.908, "m": 1211.757}, "BGR": {"m": 8.138}, "GBR": {"x": 0.0, "m": 52654.94}, "CAN": {"m": 928.512}, "USP": {"m": 3.363}, "KOR": {"x": 208781.264, "m": 6271.887}, "COL": {"x": 0.0}, "CHE": {"x": 0.0, "m": 922.201}, "SPE": {"m": 0.751}, "MYS": {"x": 2067.372, "m": 32064.864}, "SER": {"m": 24.051}, "SGP": {"x": 246517.617, "m": 149692.48}, "HUN": {"m": 18.007}, "MDG": {"m": 2.314}, "PRK": {"m": 0.597}, "PRT": {"m": 37.148}, "POL": {"m": 32.402}, "KWT": {"m": 4.377}, "NOR": {"x": 0.0, "m": 104.989}, "CHN": {"x": 0.0, "m": 12185.8}, "HKG": {"x": 0.0, "m": 9074.106}, "SAU": {"x": 0.0, "m": 0.66}, "MNG": {"m": 0.724}, "NPL": {"x": 0.0, "m": 5.32}, "VNM": {"x": 0.0, "m": 32.256}, "FRA": {"x": 0.0, "m": 7045.007}, "UNS": {"x": 4.806, "m": 12143.572}, "BLX": {"x": 0.0, "m": 923.677}, "AUT": {"m": 741.449}, "ESP": {"m": 205.369}, "IRQ": {"m": 2.909}, "CHL": {"m": 4.049}, "DNK": {"x": 0.0, "m": 4441.051}, "PAK": {"x": 0.0, "m": 58.814}, "NLD": {"x": 5.845, "m": 10799.353}, "AUS": {"x": 0.0, "m": 16784.912}, "MMR": {"x": 0.0, "m": 52.051}, "IRL": {"m": 1.411}, "GRC": {"x": 0.0, "m": 115.367}, "RUS": {"m": 0.501}, "PNG": {"x": 0.0}, "FIN": {"m": 93.997}, "THA": {"x": 315107.678, "m": 19002.354}, "NZL": {"x": 0.0, "m": 2137.073}, "KEN": {"x": 0.0}, "BHR": {"m": 1.5}, "COD": {"m": 1.674}, "JPN": {"x": 1819521.088, "m": 121662.712}, "ZAF": {"m": 20.058}, "MDV": {"m": 0.745}, "TUR": {"m": 13.812}, "PHL": {"x": 14846.945, "m": 723.106}, "ITA": {"x": 0.0, "m": 7227.949}, "MAC": {"m": 11.425}, "ARE": {"x": 0.0, "m": 41.633}, "ARG": {"m": 44.773}, "IND": {"x": 0.0, "m": 1366.188}, "OAS": {"x": 104202.491, "m": 16714.246}, "CZE": {"m": 9.243}, "MEX": {"m": 31.649}, "BRA": {"m": 903.662}, "CUB": {"m": 2.205}}, "1982": {"TLS": {"m": 1.478}, "GUF": {"m": 4.318}, "USA": {"x": 483747.242, "m": 124683.824}, "ISR": {"m": 48.842}, "USP": {"m": 0.607}, "SWE": {"x": 0.0, "m": 2680.272}, "DEU": {"x": 0.0, "m": 17817.248}, "LKA": {"x": 0.0, "m": 34.533}, "GNB": {"m": 3.88}, "GBR": {"x": 2.335, "m": 47179.964}, "CAN": {"m": 2902.976}, "ISL": {"m": 1.567}, "KOR": {"x": 161979.456, "m": 32232.488}, "CHE": {"m": 1497.83}, "KEN": {"m": 2.183}, "TZA": {"m": 1.126}, "CYP": {"m": 5.737}, "MYS": {"x": 747.672, "m": 31123.44}, "SGP": {"x": 209598.164, "m": 153570.944}, "HUN": {"m": 16.485}, "MDG": {"m": 7.188}, "PRK": {"m": 30.909}, "NGA": {"m": 0.901}, "PRT": {"m": 103.342}, "POL": {"m": 30.895}, "NLD": {"x": 2.241, "m": 20625.656}, "CHN": {"x": 0.0, "m": 13344.102}, "HKG": {"x": 0.0, "m": 9661.34}, "MNG": {"m": 4.016}, "NPL": {"m": 11.89}, "VNM": {"m": 1.205}, "FRA": {"x": 117873.419, "m": 7216.671}, "UNS": {"x": 3.337, "m": 17374.749}, "SER": {"m": 17.921}, "BLX": {"m": 1870.178}, "AUT": {"m": 654.469}, "ESP": {"m": 275.233}, "IRQ": {"m": 1.722}, "DNK": {"m": 4573.732}, "PAK": {"m": 82.272}, "NOR": {"m": 744.037}, "AUS": {"x": 0.0, "m": 17124.794}, "MMR": {"x": 0.0, "m": 24.101}, "IRL": {"m": 4.824}, "GRC": {"m": 8.246}, "IRN": {"m": 1.696}, "RUS": {"m": 6.078}, "GIN": {"m": 7.304}, "FIN": {"m": 89.031}, "THA": {"x": 97420.406, "m": 13727.944}, "NZL": {"x": 9490.203, "m": 2030.126}, "IDN": {"x": 0.0, "m": 518.429}, "MAR": {"m": 4.032}, "JPN": {"x": 2571836.849, "m": 174725.264}, "ZAF": {"m": 29.02}, "TUR": {"m": 3.628}, "PHL": {"x": 77080.64, "m": 5573.521}, "OMN": {"x": 0.0}, "ITA": {"m": 4838.158}, "ARE": {"x": 0.0, "m": 5.836}, "ARG": {"m": 24.833}, "IND": {"x": 0.0, "m": 1091.166}, "OAS": {"x": 42992.952, "m": 20991.16}, "BHS": {"m": 4.64}, "ROM": {"m": 19.587}, "MEX": {"m": 79.247}, "BRA": {"m": 228.654}, "CZE": {"m": 12.755}}, "1983": {"ATG": {"m": 7.582}, "EGY": {"m": 3.028}, "GNQ": {"m": 1.346}, "IRN": {"m": 0.545}, "USA": {"x": 271897.752, "m": 141942.432}, "ISR": {"m": 35.366}, "USP": {"m": 92.188}, "SWE": {"m": 2278.322}, "DEU": {"x": 0.0, "m": 16422.957}, "LKA": {"x": 0.0, "m": 57.153}, "GNB": {"m": 208.875}, "BGR": {"m": 1.652}, "GBR": {"x": 1.747, "m": 54874.344}, "CAN": {"x": 0.0, "m": 989.175}, "ROM": {"m": 13.723}, "KOR": {"x": 254967.9, "m": 4514.892}, "CHE": {"x": 0.0, "m": 1605.539}, "KEN": {"m": 0.807}, "CYP": {"m": 1.627}, "MYS": {"x": 1896.307, "m": 31664.906}, "SGP": {"x": 198835.477, "m": 166093.776}, "HUN": {"m": 10.526}, "MDG": {"m": 6.789}, "PRK": {"m": 28.99}, "NGA": {"m": 2.36}, "PRT": {"m": 152.803}, "POL": {"m": 36.56}, "KWT": {"m": 1.508}, "CHN": {"m": 13497.509}, "HKG": {"x": 0.0, "m": 7862.927}, "SAU": {"x": 0.0, "m": 18.731}, "MNG": {"m": 1.964}, "CUW": {"m": 23.519}, "VNM": {"x": 0.0, "m": 1.501}, "FRA": {"x": 21192.188, "m": 9396.885}, "UNS": {"x": 2.551, "m": 22898.988}, "SER": {"m": 27.026}, "BLX": {"m": 998.359}, "RUS": {"m": 6.35}, "ESP": {"m": 284.791}, "IRQ": {"m": 4.477}, "AFG": {"m": 1.17}, "CHL": {"m": 1.935}, "DNK": {"m": 6324.357}, "PAK": {"x": 0.0, "m": 67.893}, "NLD": {"x": 2.997, "m": 14559.337}, "AUS": {"x": 0.0, "m": 19534.312}, "MMR": {"x": 0.0, "m": 40.827}, "IRL": {"m": 2.52}, "AUT": {"m": 1200.702}, "GRC": {"m": 0.955}, "NPL": {"m": 4.677}, "FIN": {"m": 189.079}, "PYF": {"m": 0.552}, "THA": {"x": 157118.102, "m": 16554.466}, "NZL": {"x": 0.0, "m": 3248.442}, "IDN": {"x": 1.416, "m": 2696.75}, "CXR": {"m": 0.642}, "MAR": {"m": 5.798}, "JPN": {"x": 2293161.293, "m": 139461.808}, "ZAF": {"m": 3.98}, "TUR": {"m": 18.643}, "PHL": {"x": 57604.129, "m": 9838.973}, "OMN": {"x": 0.0}, "ITA": {"m": 13812.273}, "NOR": {"x": 0.0, "m": 105.045}, "ARG": {"m": 50.711}, "IND": {"x": 0.0, "m": 1398.334}, "OAS": {"x": 93530.368, "m": 19823.856}, "BHS": {"m": 1.076}, "CZE": {"m": 30.919}, "MEX": {"m": 98.119}, "BRA": {"m": 453.376}, "CUB": {"m": 2.341}}, "1980": {"QAT": {"m": 2.46}, "SPE": {"x": 0.0}, "GUF": {"m": 15.555}, "USA": {"x": 387691.154, "m": 113559.56}, "ISR": {"m": 64.391}, "MOZ": {"m": 3.835}, "SWE": {"m": 2177.811}, "DEU": {"x": 0.0, "m": 16571.203}, "LKA": {"x": 0.0, "m": 56.252}, "GNB": {"m": 1.582}, "BGR": {"m": 1.226}, "GBR": {"x": 0.0, "m": 55022.824}, "CAN": {"x": 0.0, "m": 1715.848}, "ISL": {"m": 1.8}, "KOR": {"x": 0.0, "m": 1082.605}, "TLS": {"m": 0.688}, "CHE": {"x": 0.0, "m": 644.092}, "KEN": {"m": 4.829}, "JOR": {"m": 0.702}, "CYP": {"m": 0.983}, "MYS": {"x": 697.916, "m": 23018.12}, "SGP": {"x": 279465.477, "m": 110356.344}, "HUN": {"m": 17.473}, "MDG": {"m": 2.167}, "PRK": {"m": 30.914}, "PRT": {"m": 104.472}, "POL": {"m": 40.289}, "USP": {"m": 12.776}, "NLD": {"x": 0.917, "m": 16469.064}, "CHN": {"m": 10335.381}, "HKG": {"x": 0.0, "m": 7928.584}, "SAU": {"x": 0.0}, "CUW": {"m": 2.782}, "VNM": {"m": 36.141}, "FRA": {"x": 0.0, "m": 7527.2}, "UNS": {"x": 4.767, "m": 10008.181}, "SER": {"m": 1.393}, "BLX": {"m": 3448.657}, "AUT": {"m": 543.758}, "ESP": {"m": 149.953}, "IRQ": {"m": 1.013}, "DNK": {"x": 0.0, "m": 3318.297}, "PAK": {"x": 0.0, "m": 71.548}, "NOR": {"m": 1024.25}, "AUS": {"x": 34379.638, "m": 9373.011}, "MMR": {"x": 0.0, "m": 13.712}, "IRL": {"m": 1.684}, "CUB": {"m": 4.184}, "IRN": {"m": 2.995}, "NPL": {"m": 1.112}, "FIN": {"m": 38.635}, "THA": {"x": 185727.658, "m": 11568.213}, "NZL": {"x": 20802.69, "m": 1939.783}, "IDN": {"m": 508.721}, "MAR": {"m": 7.329}, "COD": {"m": 98.289}, "JPN": {"x": 3203355.047, "m": 133577.024}, "ZAF": {"x": 221409.76, "m": 16.05}, "TUR": {"m": 1.407}, "PHL": {"x": 50193.941, "m": 2837.92}, "OMN": {"x": 0.0}, "ITA": {"x": 0.0, "m": 11713.993}, "UGA": {"m": 1.398}, "RUS": {"m": 151.309}, "ARE": {"m": 1.649}, "ARG": {"m": 53.938}, "IND": {"x": 0.0, "m": 891.574}, "OAS": {"x": 72795.077, "m": 6589.808}, "BHS": {"m": 0.867}, "ROM": {"m": 22.718}, "MEX": {"m": 75.763}, "BRA": {"x": 0.0, "m": 410.004}, "CZE": {"m": 12.883}}, "1981": {"GRC": {"m": 0.502}, "USA": {"x": 432977.066, "m": 111840.816}, "ISR": {"m": 108.177}, "SWE": {"m": 2082.79}, "DEU": {"x": 0.0, "m": 11137.098}, "LKA": {"x": 0.0, "m": 44.707}, "GNB": {"m": 2.873}, "GBR": {"x": 0.993, "m": 52908.404}, "CAN": {"m": 605.592}, "ISL": {"m": 2.67}, "GUY": {"m": 0.646}, "KOR": {"x": 0.0, "m": 2980.208}, "CHE": {"m": 809.753}, "KEN": {"m": 2.809}, "CYP": {"m": 7.902}, "MYS": {"x": 966.924, "m": 31351.226}, "SGP": {"x": 273327.045, "m": 141757.008}, "HUN": {"m": 100.984}, "MDG": {"m": 3.543}, "PRK": {"m": 5.149}, "PRT": {"m": 92.618}, "POL": {"m": 50.839}, "SUR": {"m": 1.283}, "NLD": {"x": 38248.37, "m": 8402.289}, "CHN": {"m": 13020.732}, "HKG": {"x": 0.0, "m": 6856.897}, "SAU": {"x": 0.0}, "MNG": {"m": 0.553}, "CUW": {"x": 81979.216, "m": 62.235}, "VNM": {"x": 0.0, "m": 1.134}, "FRA": {"x": 18098.304, "m": 5464.626}, "UNS": {"x": 3.29, "m": 11436.535}, "SER": {"m": 4.089}, "BLX": {"m": 1316.901}, "AUT": {"m": 314.404}, "ESP": {"m": 367.674}, "IRQ": {"m": 1.563}, "DNK": {"m": 4731.331}, "PAK": {"x": 0.0, "m": 56.341}, "NOR": {"x": 0.0, "m": 757.405}, "AUS": {"x": 23602.533, "m": 13004.028}, "MMR": {"x": 0.0, "m": 24.345}, "IRL": {"m": 15.356}, "CUB": {"m": 3.711}, "IRN": {"m": 1.75}, "NPL": {"m": 7.244}, "GIN": {"m": 2.838}, "FIN": {"m": 47.892}, "PNG": {"m": 9.868}, "NZL": {"x": 0.0, "m": 1969.355}, "IDN": {"x": 8.501, "m": 613.608}, "CXR": {"m": 1.765}, "MAR": {"m": 15.703}, "COD": {"m": 63.118}, "JPN": {"x": 2803246.375, "m": 133940.816}, "ZAF": {"x": 100287.781, "m": 27.545}, "TUR": {"m": 2.525}, "PHL": {"x": 121090.316, "m": 2680.521}, "THA": {"x": 128435.397, "m": 14933.973}, "ITA": {"x": 0.0, "m": 6423.989}, "RUS": {"m": 32.694}, "ARE": {"x": 0.0, "m": 4.061}, "ARG": {"m": 2.026}, "IND": {"x": 0.0, "m": 1030.689}, "OAS": {"x": 0.0, "m": 12196.955}, "BHS": {"m": 5.25}, "ROM": {"m": 28.249}, "MEX": {"m": 45.539}, "BRA": {"m": 365.317}, "CZE": {"m": 14.428}}, "1964": {"VDR": {"m": 3.198}, "USA": {"x": 0.0, "m": 3555.632}, "SWE": {"m": 64.443}, "DEU": {"x": 1.959, "m": 1295.305}, "LKA": {"m": 37.834}, "IDN": {"m": 76.66}, "GBR": {"x": 12.651, "m": 9052.485}, "CAN": {"x": 0.0, "m": 202.79}, "KOR": {"m": 6.27}, "CHE": {"m": 75.572}, "CYP": {"m": 0.617}, "MYS": {"x": 58645.499, "m": 1543.024}, "SGP": {"x": 634.62, "m": 4185.486}, "HUN": {"m": 2.489}, "PRT": {"m": 0.662}, "TTO": {"m": 3.166}, "KHM": {"m": 1.168}, "HKG": {"x": 14.518, "m": 1274.633}, "NLD": {"x": 1.039, "m": 2002.69}, "SVR": {"m": 31.977}, "FRA": {"m": 231.229}, "UNS": {"x": 59.683, "m": 975.374}, "BLX": {"m": 80.329}, "AUT": {"m": 32.25}, "ESP": {"m": 9.233}, "DNK": {"m": 205.346}, "PAK": {"m": 1.22}, "AUS": {"x": 43.731, "m": 1101.344}, "MMR": {"m": 5.831}, "CHN": {"x": 0.0, "m": 1318.94}, "IRN": {"m": 2.08}, "RUS": {"m": 12.117}, "FIN": {"m": 7.017}, "URY": {"m": 1.763}, "THA": {"x": 0.0, "m": 1450.024}, "NZL": {"m": 16.902}, "MAR": {"m": 29.826}, "JPN": {"x": 0.0, "m": 1869.336}, "ZAF": {"m": 71.378}, "PHL": {"m": 11.978}, "ITA": {"m": 189.232}, "ARG": {"m": 8.139}, "IND": {"m": 78.831}, "OAS": {"m": 318.929}, "BHR": {"m": 4.974}, "MEX": {"m": 0.919}, "NOR": {"m": 2.761}, "CZE": {"m": 7.243}}, "1979": {"ATG": {"m": 15.522}, "EGY": {"m": 9.414}, "USA": {"x": 221475.117, "m": 66193.208}, "QAT": {"x": 0.0}, "ISR": {"m": 44.03}, "MOZ": {"m": 6.739}, "SWE": {"m": 1765.446}, "DEU": {"x": 0.0, "m": 8272.203}, "LKA": {"x": 0.0, "m": 39.518}, "GNB": {"m": 0.675}, "GBR": {"x": 0.0, "m": 39169.484}, "CAN": {"x": 0.0, "m": 263.772}, "USP": {"m": 15.567}, "KOR": {"m": 942.653}, "CHE": {"x": 0.0, "m": 537.544}, "KEN": {"m": 4.797}, "CYP": {"m": 0.708}, "MYS": {"x": 347.72, "m": 16807.314}, "SGP": {"x": 152600.439, "m": 83739.6}, "HUN": {"m": 12.534}, "MDG": {"m": 1.313}, "PRK": {"m": 55.455}, "PRT": {"m": 71.264}, "POL": {"m": 50.009}, "KHM": {"m": 4.16}, "CHN": {"m": 10862.442}, "HKG": {"x": 0.0, "m": 7307.57}, "SAU": {"m": 5.496}, "NLD": {"x": 0.0, "m": 3941.784}, "CUW": {"m": 0.579}, "FRA": {"x": 68366.168, "m": 6271.003}, "UNS": {"x": 2.757, "m": 8218.82}, "SER": {"m": 3.235}, "BLX": {"x": 0.0, "m": 838.707}, "ESP": {"m": 113.995}, "IRQ": {"m": 5.872}, "DNK": {"x": 0.0, "m": 1653.582}, "PAK": {"m": 79.983}, "ROM": {"m": 32.961}, "AUS": {"x": 19.083, "m": 8723.07}, "MMR": {"m": 69.944}, "AUT": {"m": 193.071}, "IRN": {"m": 37.151}, "RUS": {"m": 25.996}, "GIN": {"m": 1.119}, "FIN": {"m": 120.329}, "PNG": {"m": 1.21}, "NZL": {"x": 0.0, "m": 1347.327}, "IDN": {"m": 644.133}, "MAR": {"m": 0.877}, "COD": {"m": 179.988}, "JPN": {"x": 1877978.834, "m": 101124.2}, "ZAF": {"x": 97912.52, "m": 1198.411}, "PHL": {"x": 39242.345, "m": 1945.909}, "THA": {"x": 39812.48, "m": 8570.764}, "ITA": {"x": 0.0, "m": 2250.275}, "SYR": {"m": 0.959}, "NOR": {"m": 415.417}, "ARG": {"m": 42.014}, "IND": {"m": 848.931}, "OAS": {"x": 110073.682, "m": 5633.864}, "CZE": {"m": 23.976}, "MEX": {"m": 74.463}, "BRA": {"m": 405.825}, "CUB": {"m": 3.956}}, "1966": {"EGY": {"m": 2.589}, "VDR": {"m": 11.043}, "USA": {"x": 0.0, "m": 5411.182}, "ISR": {"m": 6.271}, "SWE": {"m": 134.376}, "DEU": {"x": 6.989, "m": 1928.08}, "LKA": {"m": 45.322}, "IDN": {"m": 88.882}, "GBR": {"x": 11.795, "m": 13172.273}, "CAN": {"m": 234.578}, "KOR": {"m": 50.913}, "CHE": {"m": 93.279}, "CYP": {"m": 1.047}, "MYS": {"x": 70770.425, "m": 2334.715}, "SGP": {"x": 397.32, "m": 6574.231}, "HUN": {"m": 1.185}, "PRT": {"m": 9.083}, "POL": {"m": 2.516}, "TTO": {"m": 1.396}, "KHM": {"m": 10.924}, "HKG": {"x": 1.972, "m": 1449.398}, "NLD": {"x": 2.365, "m": 2098.301}, "SVR": {"m": 13.75}, "FRA": {"x": 0.837, "m": 634.842}, "UNS": {"x": 5.935, "m": 1221.433}, "SER": {"m": 223.402}, "BLX": {"x": 1.349, "m": 685.094}, "AUT": {"m": 139.26}, "ESP": {"m": 8.924}, "ZMB": {"m": 33.802}, "IRQ": {"m": 0.696}, "DNK": {"m": 260.947}, "PAK": {"m": 7.66}, "AUS": {"x": 5.314, "m": 1565.756}, "MMR": {"m": 1.41}, "CHN": {"m": 2439.143}, "RUS": {"m": 19.908}, "FIN": {"m": 8.068}, "THA": {"m": 1847.683}, "NZL": {"x": 0.0, "m": 24.759}, "MAR": {"m": 13.056}, "JPN": {"x": 26.642, "m": 4417.94}, "ZAF": {"m": 58.558}, "PHL": {"x": 0.0, "m": 9.479}, "ITA": {"m": 1346.891}, "ARG": {"m": 6.698}, "IND": {"m": 122.311}, "OAS": {"x": 20.717, "m": 213.184}, "BHR": {"m": 1.639}, "MEX": {"m": 5.523}, "NOR": {"m": 7.188}, "CZE": {"m": 1.843}}, "1967": {"USA": {"x": 0.0, "m": 3858.026}, "ISR": {"m": 5.035}, "SWE": {"m": 106.35}, "DEU": {"x": 3.451, "m": 1013.796}, "LKA": {"x": 0.0, "m": 39.593}, "IDN": {"m": 106.547}, "GBR": {"x": 25.558, "m": 10439.589}, "CAN": {"m": 474.996}, "KOR": {"m": 4.82}, "CHE": {"m": 77.281}, "CYP": {"m": 0.96}, "MYS": {"x": 78501.894, "m": 2934.735}, "SGP": {"x": 248.409, "m": 7679.666}, "HUN": {"m": 1.181}, "TZA": {"m": 0.775}, "PRT": {"m": 13.143}, "POL": {"m": 0.705}, "TTO": {"m": 1.913}, "KHM": {"m": 2.043}, "HKG": {"x": 11.531, "m": 1976.179}, "SAU": {"m": 1.646}, "NLD": {"x": 1.177, "m": 810.624}, "SVR": {"m": 1.68}, "FRA": {"x": 0.0, "m": 493.919}, "UNS": {"x": 5.218, "m": 1428.883}, "BLX": {"m": 170.009}, "AUT": {"m": 61.105}, "ESP": {"m": 8.636}, "ZMB": {"m": 0.576}, "IRQ": {"m": 0.503}, "DNK": {"m": 271.412}, "PAK": {"m": 5.7}, "ROM": {"m": 1.604}, "AUS": {"x": 2.028, "m": 1574.795}, "MMR": {"m": 6.062}, "CHN": {"m": 2657.506}, "RUS": {"m": 17.051}, "FIN": {"m": 5.909}, "THA": {"x": 0.0, "m": 2429.911}, "NZL": {"x": 0.0, "m": 25.277}, "MAR": {"m": 41.385}, "JPN": {"x": 8.983, "m": 3289.413}, "ZAF": {"m": 92.389}, "PHL": {"m": 10.401}, "ITA": {"x": 0.0, "m": 296.575}, "ARG": {"m": 7.599}, "IND": {"x": 0.0, "m": 114.134}, "OAS": {"x": 0.0, "m": 175.713}, "BHR": {"m": 0.819}, "MEX": {"m": 0.519}, "NOR": {"m": 18.289}, "CZE": {"m": 1.656}}, "1988": {"EGY": {"x": 0.0, "m": 3.721}, "BGD": {"m": 3.349}, "MUS": {"m": 2.724}, "ISR": {"m": 7.092}, "SWE": {"x": 0.0, "m": 3284.084}, "FJI": {"m": 2.729}, "LKA": {"m": 16.409}, "IDN": {"x": 149.076, "m": 9299.846}, "BGR": {"m": 6.626}, "GBR": {"x": 190.467, "m": 51738.132}, "CAN": {"x": 0.0, "m": 1158.769}, "ISL": {"m": 18.564}, "KOR": {"x": 177360.104, "m": 11074.06}, "COL": {"m": 4.305}, "CHE": {"x": 0.0, "m": 2709.389}, "JOR": {"m": 17.399}, "CYP": {"m": 9.604}, "MYS": {"x": 1731.854, "m": 58594.308}, "SGP": {"x": 83677.952, "m": 196953.536}, "HUN": {"m": 113.981}, "MDG": {"m": 6.866}, "PRK": {"m": 2.875}, "PRT": {"m": 59.744}, "POL": {"m": 36.502}, "NLD": {"x": 54.478, "m": 15798.139}, "USA": {"x": 34778.409, "m": 93569.936}, "HKG": {"x": 192.904, "m": 8459.601}, "SAU": {"m": 3.63}, "MNG": {"m": 0.653}, "CUW": {"m": 7.327}, "VNM": {"x": 0.0, "m": 44.578}, "FRA": {"x": 0.0, "m": 11253.576}, "UNS": {"x": 6.606, "m": 3558.61}, "SER": {"m": 56.436}, "BLX": {"m": 1728.396}, "AUT": {"m": 1726.29}, "ESP": {"m": 698.864}, "IRQ": {"m": 13.891}, "GRC": {"m": 36.391}, "CHL": {"x": 0.0, "m": 259.237}, "DNK": {"x": 0.0, "m": 4181.641}, "DEU": {"x": 0.0, "m": 34678.964}, "PAK": {"x": 0.0, "m": 191.971}, "NOR": {"x": 0.0, "m": 219.367}, "AUS": {"x": 21703.066, "m": 24662.486}, "MMR": {"x": 0.0, "m": 54.56}, "IRL": {"m": 35.182}, "CHN": {"x": 5367.43, "m": 15641.801}, "IRN": {"m": 45.565}, "RUS": {"x": 0.0, "m": 3.811}, "FIN": {"m": 172.795}, "URY": {"m": 29.398}, "THA": {"x": 150137.329, "m": 30010.356}, "NZL": {"x": 0.839, "m": 2879.269}, "NPL": {"x": 0.0, "m": 4.856}, "JPN": {"x": 1110669.473, "m": 118668.576}, "TUR": {"m": 32.266}, "PHL": {"x": 33827.078, "m": 918.785}, "ITA": {"x": 0.0, "m": 11803.352}, "MAC": {"m": 12.609}, "ARE": {"x": 0.0, "m": 11.959}, "ARG": {"m": 300.42}, "IND": {"m": 1587.377}, "OAS": {"x": 49728.121, "m": 17222.416}, "ROM": {"m": 49.973}, "MEX": {"x": 0.0, "m": 71.116}, "BRA": {"m": 1612.547}, "CZE": {"m": 21.812}}, "1989": {"QAT": {"x": 0.0}, "EGY": {"x": 0.0, "m": 24.968}, "BGD": {"m": 0.615}, "NGA": {"x": 0.0, "m": 2.663}, "MUS": {"m": 3.668}, "ISR": {"m": 21.363}, "SWE": {"m": 5553.011}, "DEU": {"x": 0.0, "m": 37865.164}, "PER": {"m": 1.379}, "LKA": {"m": 13.543}, "IDN": {"x": 110.239, "m": 14822.205}, "BGR": {"m": 9.54}, "UNS": {"x": 2.523, "m": 2842.963}, "GBR": {"x": 65.847, "m": 73099.056}, "CAN": {"x": 81.983, "m": 1665.07}, "ISL": {"m": 2.473}, "KOR": {"x": 247388.476, "m": 8776.144}, "COL": {"x": 0.0}, "CHE": {"x": 0.0, "m": 2930.631}, "JOR": {"m": 5.454}, "CYP": {"m": 16.227}, "MYS": {"x": 1326.432, "m": 77973.976}, "SYR": {"x": 0.0}, "LBY": {"x": 0.0}, "NRU": {"m": 1.971}, "HUN": {"m": 82.812}, "MDG": {"m": 16.535}, "PRK": {"m": 30.58}, "TZA": {"m": 3.162}, "PRT": {"m": 98.45}, "POL": {"m": 265.96}, "KWT": {"m": 6.103}, "USA": {"x": 91226.417, "m": 108779.176}, "YDR": {"m": 483.192}, "HKG": {"x": 183.383, "m": 9933.893}, "SAU": {"x": 0.0, "m": 9.825}, "NLD": {"x": 1.258, "m": 14272.966}, "NPL": {"x": 0.0, "m": 0.658}, "VNM": {"x": 0.0, "m": 171.915}, "FRA": {"x": 0.0, "m": 14081.795}, "ROM": {"m": 75.614}, "SER": {"m": 9.435}, "BLX": {"m": 1654.566}, "AUT": {"m": 6287.903}, "ESP": {"x": 0.0, "m": 1117.892}, "IRQ": {"m": 1.815}, "GRC": {"m": 2.523}, "CHL": {"m": 153.367}, "DNK": {"m": 6244.44}, "PAK": {"m": 217.334}, "NOR": {"x": 0.0, "m": 930.528}, "AUS": {"x": 17117.472, "m": 17625.414}, "MMR": {"x": 0.0, "m": 16.933}, "IRL": {"m": 421.181}, "CHN": {"x": 7692.997, "m": 19764.45}, "IRN": {"m": 57.392}, "RUS": {"m": 11.112}, "PNG": {"x": 0.0}, "FIN": {"m": 1084.177}, "URY": {"m": 55.895}, "THA": {"x": 194065.403, "m": 32868.852}, "NZL": {"x": 0.0, "m": 2824.51}, "MOZ": {"m": 7.825}, "MAR": {"m": 8.89}, "JPN": {"x": 1094723.916, "m": 126412.816}, "TUR": {"m": 61.8}, "PHL": {"x": 47700.95, "m": 952.105}, "OMN": {"x": 0.0, "m": 2.547}, "ITA": {"x": 0.0, "m": 15315.362}, "SGP": {"x": 66549.256, "m": 231130.304}, "MAC": {"m": 73.947}, "ARE": {"x": 0.0, "m": 232.816}, "ARG": {"m": 339.371}, "IND": {"x": 0.0, "m": 1326.847}, "OAS": {"x": 63871.599, "m": 13048.244}, "BHR": {"x": 0.0}, "MEX": {"x": 0.0, "m": 63.449}, "BRA": {"m": 2081.643}, "CZE": {"x": 0.0, "m": 34.283}}, "2015": {"QAT": {"x": 1065.511, "m": 1656.763}, "EGY": {"x": 2441.836, "m": 844.952}, "BGD": {"x": 9.42, "m": 607.946}, "BGR": {"m": 89.852}, "OAS": {"x": 436508.543, "m": 26306.65}, "GHA": {"x": 4.702, "m": 4.175}, "PAK": {"x": 134.431, "m": 811.074}, "WLF": {"m": 0.017}, "JOR": {"x": 0.007, "m": 291.849}, "LBR": {"m": 4.382}, "LBY": {"m": 4.795}, "MYS": {"x": 293642.113, "m": 682462.526}, "DOM": {"m": 2.628}, "PRK": {"x": 102.852, "m": 738.31}, "TZA": {"x": 125.38, "m": 1.713}, "PRT": {"x": 86.956, "m": 3418.856}, "KHM": {"x": 6.568, "m": 45.901}, "TTO": {"m": 0.303}, "HKG": {"x": 7411.149, "m": 27972.867}, "SAU": {"x": 933.015, "m": 2096.398}, "LBN": {"m": 201.057}, "CHE": {"x": 243.883, "m": 10563.701}, "CHL": {"x": 14.733, "m": 313.989}, "CHN": {"x": 96465.766, "m": 336710.287}, "JAM": {"m": 10.065}, "FIN": {"m": 3170.416}, "URY": {"m": 128.119}, "THA": {"x": 548605.836, "m": 121062.785}, "SYC": {"m": 10.213}, "NPL": {"x": 93.295, "m": 46.284}, "CXR": {"m": 11.897}, "MAR": {"x": 0.036, "m": 10.221}, "PHL": {"x": 24827.846, "m": 8353.496}, "ZAF": {"m": 1990.215}, "SYR": {"m": 3.776}, "MAC": {"x": 91.122, "m": 24.704}, "MLT": {"m": 0.287}, "NGA": {"x": 140.672, "m": 1.203}, "BEL": {"x": 91.623, "m": 5871.319}, "DEU": {"x": 5691.368, "m": 168249.43}, "LKA": {"x": 60.397, "m": 136.899}, "GBR": {"x": 10308.72, "m": 84041.891}, "MWI": {"m": 99.115}, "ITA": {"x": 97.633, "m": 62731.985}, "ROM": {"x": 1.418, "m": 376.134}, "HUN": {"m": 1130.588}, "BUN": {"x": 7.887}, "NLD": {"x": 4300.625, "m": 28414.788}, "TCD": {"m": 89.86}, "AFG": {"m": 8.447}, "BDI": {"m": 10.581}, "GRC": {"x": 249.259, "m": 478.483}, "MOZ": {"m": 0.171}, "HTI": {"m": 0.062}, "IND": {"x": 575321.154, "m": 36369.292}, "VCT": {"m": 2.127}, "VNM": {"x": 47153.344, "m": 38239.242}, "NOR": {"x": 474.02, "m": 6433.843}, "CZE": {"x": 0.001, "m": 548.196}, "SUD": {"x": 0.744}, "HND": {"m": 3.048}, "MUS": {"m": 38.158}, "ATA": {"m": 312.956}, "LUX": {"m": 86.426}, "ISR": {"m": 15.036}, "PER": {"x": 20.411, "m": 179.299}, "IDN": {"x": 102635.44, "m": 86339.435}, "SUR": {"m": 7.205}, "ISL": {"x": 0.689, "m": 10.186}, "UMI": {"m": 192.71}, "COL": {"x": 0.023, "m": 6.468}, "SER": {"m": 5.13}, "MDG": {"m": 22.623}, "ECU": {"x": 0.251, "m": 4.078}, "SEN": {"m": 0.756}, "MDV": {"m": 50.361}, "CUW": {"x": 0.109}, "FRA": {"x": 432.706, "m": 26674.824}, "UNS": {"x": 298.538, "m": 29678.11}, "VAT": {"m": 0.267}, "GTM": {"m": 22.964}, "DNK": {"x": 26.331, "m": 2976.26}, "AUS": {"x": 221848.108, "m": 43839.256}, "AUT": {"x": 23.381, "m": 1663.856}, "VEN": {"x": 25.26, "m": 3.275}, "KEN": {"x": 0.65, "m": 0.967}, "LAO": {"x": 14.707, "m": 0.242}, "TUR": {"x": 133.374, "m": 4397.928}, "ALB": {"x": 0.364, "m": 0.174}, "OMN": {"x": 690.339, "m": 1396.606}, "MMR": {"x": 27.622, "m": 306.7}, "TUN": {"x": 3.645, "m": 13.566}, "RUS": {"x": 51.48}, "MEX": {"x": 23.547, "m": 6100.232}, "BRA": {"x": 40.136, "m": 786.098}, "CIV": {"m": 4566.919}, "MKD": {"m": 0.184}, "USA": {"x": 52710.894, "m": 331632.324}, "SWE": {"x": 0.613, "m": 3119.57}, "UKR": {"m": 8.621}, "SWZ": {"m": 99.439}, "CAN": {"x": 657.06, "m": 5414.6}, "KOR": {"x": 993010.909, "m": 292573.781}, "AIA": {"m": 954.336}, "SVK": {"m": 402.037}, "CYP": {"x": 7.33, "m": 4.638}, "BIH": {"m": 0.187}, "SGP": {"x": 222165.576, "m": 451044.216}, "SOM": {"m": 32.178}, "POL": {"m": 668.441}, "KWT": {"x": 57590.772, "m": 11.599}, "ESP": {"x": 33.597, "m": 4381.531}, "IRQ": {"x": 0.168, "m": 2.877}, "IRL": {"m": 4441.693}, "IRN": {"x": 0.416, "m": 142.389}, "SLE": {"m": 35.459}, "SLB": {"m": 0.264}, "NZL": {"x": 331931.095, "m": 4847.139}, "JPN": {"x": 2308974.356, "m": 239345.541}, "ARE": {"x": 735.952, "m": 7838.999}, "ARG": {"x": 26.815, "m": 6801.051}, "BHR": {"x": 11.176, "m": 0.481}, "PNG": {"x": 1791.568, "m": 3.06}, "CUB": {"m": 0.055}}, "2014": {"QAT": {"x": 26.921, "m": 4.884}, "EGY": {"x": 68.825, "m": 798.584}, "BGD": {"x": 35.7, "m": 320.515}, "BGR": {"m": 81.797}, "OAS": {"x": 580075.311, "m": 35605.211}, "GHA": {"m": 62.128}, "PAK": {"x": 133.464, "m": 1004.219}, "WLF": {"m": 0.088}, "JOR": {"x": 18.715, "m": 89.698}, "MYS": {"x": 370408.274, "m": 741053.75}, "DOM": {"m": 5.975}, "PRK": {"m": 307.836}, "TZA": {"m": 85.72}, "PRT": {"x": 0.001, "m": 4222.101}, "KHM": {"x": 39.217, "m": 2755.194}, "HKG": {"x": 6264.538, "m": 28555.014}, "SAU": {"x": 345.963, "m": 2274.757}, "LBN": {"x": 5.031, "m": 177.369}, "CHE": {"x": 11.949, "m": 13034.757}, "CHL": {"x": 0.706, "m": 131.292}, "CHN": {"x": 95382.869, "m": 357884.202}, "JAM": {"m": 0.958}, "FIN": {"x": 58.366, "m": 951.25}, "URY": {"m": 83.663}, "THA": {"x": 547588.584, "m": 161869.238}, "NPL": {"x": 281.544, "m": 21.659}, "CXR": {"m": 3.688}, "MAR": {"x": 9.02, "m": 5.288}, "PHL": {"x": 76382.212, "m": 9376.345}, "ZAF": {"m": 3946.647}, "SYR": {"x": 219.51, "m": 1.529}, "MAC": {"m": 35.247}, "MLT": {"m": 0.07}, "NGA": {"x": 371.165, "m": 0.448}, "BEL": {"m": 4948.734}, "DEU": {"x": 4243.829, "m": 155166.927}, "LKA": {"x": 166.189, "m": 164.258}, "GBR": {"x": 6887.183, "m": 86197.777}, "MWI": {"m": 70.507}, "ITA": {"x": 280570.758, "m": 57259.578}, "CMR": {"m": 3.214}, "ROM": {"m": 1258.829}, "HUN": {"m": 321.879}, "TTO": {"m": 1.521}, "NLD": {"x": 5966.7, "m": 60635.752}, "BMU": {"m": 18.718}, "TCD": {"m": 65.229}, "BLZ": {"m": 4.037}, "AFG": {"m": 5.612}, "GRC": {"x": 0.207, "m": 159.943}, "MOZ": {"m": 2.228}, "IND": {"x": 957138.369, "m": 46693.509}, "VCT": {"m": 3.852}, "VNM": {"x": 101973.62, "m": 10076.218}, "NOR": {"x": 478.283, "m": 6465.401}, "CZE": {"x": 0.016, "m": 455.83}, "FJI": {"m": 0.218}, "SUD": {"m": 5.072}, "HND": {"m": 2.243}, "MUS": {"m": 8.475}, "ATA": {"m": 21.247}, "LUX": {"m": 235.585}, "ISR": {"m": 9.058}, "PER": {"m": 9.751}, "IDN": {"x": 637063.49, "m": 104432.063}, "COD": {"m": 0.088}, "ISL": {"m": 41.49}, "UMI": {"m": 11.857}, "COL": {"m": 6.111}, "SER": {"m": 17.262}, "MDG": {"m": 49.572}, "SEN": {"m": 0.028}, "MDV": {"m": 10.605}, "FRA": {"x": 354.956, "m": 21762.697}, "UNS": {"x": 1576.335, "m": 13015.071}, "VAT": {"m": 31.251}, "GTM": {"m": 29.03}, "DNK": {"x": 216.5, "m": 4283.518}, "AUS": {"x": 795494.255, "m": 49367.483}, "CUB": {"m": 0.555}, "VEN": {"m": 5.917}, "KEN": {"x": 98.043, "m": 0.418}, "LAO": {"x": 22.825, "m": 0.138}, "TUR": {"x": 13.461, "m": 6660.457}, "ALB": {"x": 0.039, "m": 3.104}, "OMN": {"x": 1254.995, "m": 1420.799}, "MMR": {"x": 59.292, "m": 680.554}, "TUN": {"x": 88.481, "m": 36.186}, "RUS": {"x": 166.815}, "MEX": {"m": 6823.136}, "BRA": {"x": 224.504, "m": 1055.663}, "USA": {"x": 19760.29, "m": 324755.884}, "SWE": {"x": 30.76, "m": 4361.643}, "UKR": {"m": 348.183}, "SWZ": {"m": 2863.932}, "CAN": {"x": 243832.053, "m": 33834.531}, "KOR": {"x": 1152075.731, "m": 312886.149}, "SVK": {"m": 911.847}, "CYP": {"m": 61.433}, "SGP": {"x": 342557.648, "m": 734914.038}, "SOM": {"m": 184.235}, "POL": {"x": 46.896, "m": 892.745}, "KWT": {"x": 23.986, "m": 4.621}, "TGO": {"m": 1.228}, "ESP": {"x": 43.076, "m": 3708.996}, "IRQ": {"x": 0.004}, "MLI": {"m": 0.111}, "IRL": {"m": 4053.13}, "IRN": {"x": 9.663, "m": 305.002}, "SLE": {"m": 44.543}, "SLB": {"m": 0.853}, "NZL": {"x": 365315.474, "m": 11761.078}, "JPN": {"x": 3910751.887, "m": 144974.498}, "ARE": {"x": 1890.935, "m": 6837.355}, "ARG": {"x": 17.335, "m": 3810.405}, "BHS": {"m": 0.097}, "BHR": {"x": 137.027, "m": 6.879}, "PNG": {"x": 553.072}, "AUT": {"x": 0.016, "m": 538.269}}, "2013": {"QAT": {"x": 397.316, "m": 5.228}, "EGY": {"x": 135.612, "m": 1160.532}, "BGD": {"x": 31.022, "m": 284.14}, "BGR": {"m": 16.72}, "BOL": {"m": 91.642}, "GHA": {"m": 15.791}, "PAK": {"x": 69.507, "m": 497.637}, "JOR": {"m": 6.354}, "MYS": {"x": 444537.424, "m": 791936.37}, "PRK": {"m": 289.102}, "TZA": {"m": 27.863}, "BWA": {"m": 0.492}, "KHM": {"x": 1.04, "m": 47.5}, "HKG": {"x": 4206.789, "m": 39434.074}, "SAU": {"x": 305.507, "m": 1690.942}, "LBN": {"m": 233.466}, "CHE": {"x": 64.915, "m": 8282.924}, "CHL": {"x": 62.639, "m": 278.621}, "CHN": {"x": 156245.908, "m": 406294.857}, "JAM": {"m": 31.624}, "FIN": {"m": 1308.971}, "URY": {"m": 240.63}, "THA": {"x": 481223.323, "m": 180476.88}, "SYC": {"m": 4.061}, "NPL": {"x": 62.609, "m": 20.111}, "CXR": {"m": 0.206}, "MAR": {"x": 1.306, "m": 19.873}, "YEM": {"m": 56.018}, "PHL": {"x": 82620.447, "m": 12336.243}, "ZAF": {"m": 2493.566}, "SYR": {"m": 0.308}, "MAC": {"m": 8.475}, "MLT": {"m": 0.857}, "OAS": {"x": 8274.288, "m": 38921.895}, "NGA": {"x": 652.334, "m": 0.047}, "BEL": {"x": 9.199, "m": 7753.018}, "DEU": {"x": 2565.892, "m": 124530.042}, "GUM": {"m": 0.365}, "LKA": {"x": 15.173, "m": 466.803}, "GBR": {"x": 10088.737, "m": 73054.251}, "MWI": {"m": 182.222}, "ITA": {"x": 149.159, "m": 42685.661}, "ROM": {"m": 260.302}, "HUN": {"m": 601.358}, "TTO": {"m": 1.155}, "NLD": {"x": 2673.264, "m": 46478.437}, "BMU": {"m": 1.088}, "TCD": {"m": 55.296}, "MHL": {"m": 0.351}, "AFG": {"m": 8.587}, "GRC": {"m": 18.481}, "MOZ": {"x": 0.96, "m": 0.15}, "IND": {"x": 864086.048, "m": 31354.056}, "VCT": {"m": 15.918}, "BTN": {"m": 0.137}, "VNM": {"x": 602303.668, "m": 10357.26}, "NOR": {"x": 438.526, "m": 8999.477}, "CZE": {"x": 16.498, "m": 328.706}, "FJI": {"x": 18.239, "m": 0.099}, "HND": {"m": 1.671}, "MUS": {"m": 6.944}, "DOM": {"m": 6.276}, "LUX": {"m": 650.323}, "ISR": {"m": 6.265}, "PER": {"m": 2.694}, "IDN": {"x": 538917.28, "m": 157476.497}, "ISL": {"x": 239.315, "m": 36.259}, "UMI": {"m": 28.767}, "COL": {"m": 29.851}, "SER": {"m": 5.925}, "PRT": {"m": 3002.462}, "MDG": {"m": 24.21}, "ECU": {"m": 0.514}, "SEN": {"m": 20.597}, "MDV": {"m": 40.889}, "FRA": {"x": 312.424, "m": 17139.969}, "UNS": {"x": 292.606, "m": 18594.539}, "ZMB": {"x": 3.664}, "WSM": {"x": 6.522}, "GTM": {"m": 37.698}, "DNK": {"x": 237.797, "m": 6059.042}, "ZWE": {"m": 0.202}, "AUS": {"x": 837517.744, "m": 50362.745}, "AUT": {"x": 1.136, "m": 867.768}, "VEN": {"x": 160.361, "m": 0.054}, "KEN": {"m": 2.813}, "LAO": {"x": 0.24, "m": 0.123}, "TUR": {"x": 19.712, "m": 4128.608}, "OMN": {"x": 939.882, "m": 588.729}, "MMR": {"x": 35.557, "m": 856.761}, "TUN": {"x": 4.598, "m": 9.808}, "RUS": {"x": 17.911}, "MEX": {"x": 10.477, "m": 7792.323}, "BRA": {"x": 14.329, "m": 2486.525}, "USA": {"x": 9079.552, "m": 431473.358}, "SWE": {"m": 3186.287}, "UKR": {"m": 227.41}, "SWZ": {"m": 0.467}, "TON": {"m": 0.509}, "CAN": {"x": 2189.896, "m": 9489.857}, "KOR": {"x": 1867075.297, "m": 124383.858}, "SVK": {"m": 1234.29}, "CYP": {"m": 52.225}, "BIH": {"m": 110.976}, "SGP": {"x": 501121.163, "m": 687750.766}, "SOM": {"m": 793.155}, "POL": {"x": 44.252, "m": 960.003}, "KWT": {"x": 50.529, "m": 4.596}, "TGO": {"m": 2.123}, "ESP": {"x": 54.23, "m": 4538.629}, "MLI": {"m": 2.335}, "IRL": {"m": 4623.115}, "IRN": {"x": 0.245, "m": 108.577}, "ABW": {"m": 0.759}, "SLE": {"m": 14.032}, "NZL": {"x": 472239.348, "m": 10505.917}, "JPN": {"x": 4553392.802, "m": 208980.523}, "ARE": {"x": 933.631, "m": 9646.05}, "ARG": {"x": 9.75, "m": 6560.317}, "BHS": {"m": 0.608}, "BHR": {"x": 42.338, "m": 11.006}, "UGA": {"x": 4.676}, "PNG": {"x": 885.776, "m": 0.065}}, "2012": {"DZA": {"x": 0.08, "m": 2.021}, "QAT": {"x": 767.321, "m": 2.353}, "EGY": {"x": 30.104, "m": 515.585}, "BGD": {"x": 22.752, "m": 67.997}, "BGR": {"m": 41.88}, "OAS": {"x": 32060.44, "m": 50050.027}, "GHA": {"m": 0.996}, "PAK": {"x": 23.342, "m": 673.786}, "PAN": {"m": 0.94}, "JOR": {"x": 220.655, "m": 226.591}, "MYS": {"x": 89207.8, "m": 709551.949}, "PRK": {"m": 597.169}, "TZA": {"m": 2.838}, "PRT": {"m": 384.171}, "KHM": {"x": 7.702, "m": 43.594}, "HKG": {"x": 4406.055, "m": 44377.189}, "SAU": {"x": 723.944, "m": 1700.065}, "LBN": {"x": 0.075, "m": 160.471}, "CHE": {"x": 27.616, "m": 9950.284}, "CHL": {"m": 148.531}, "CHN": {"x": 348948.919, "m": 406677.951}, "JAM": {"m": 0.191}, "FIN": {"m": 3015.71}, "URY": {"m": 809.5}, "THA": {"x": 473029.204, "m": 208463.641}, "SYC": {"m": 2.281}, "NPL": {"x": 48.35, "m": 55.174}, "CXR": {"m": 0.398}, "MAR": {"x": 24.045, "m": 88.054}, "PHL": {"x": 60539.0, "m": 10800.743}, "ZAF": {"m": 3724.345}, "SYR": {"m": 7.271}, "MAC": {"m": 8.691}, "MLT": {"m": 504.515}, "BOL": {"m": 10.624}, "NGA": {"x": 515.327, "m": 2.399}, "BEL": {"x": 75.246, "m": 7577.835}, "DEU": {"x": 14819.264, "m": 98637.529}, "LKA": {"x": 56.694, "m": 203.848}, "GBR": {"x": 10087.08, "m": 92802.062}, "MWI": {"m": 208.939}, "ITA": {"x": 456.83, "m": 61318.568}, "ROM": {"m": 307.178}, "HUN": {"m": 745.197}, "TTO": {"m": 7.795}, "NLD": {"x": 2683.423, "m": 32241.824}, "BMU": {"m": 1.017}, "TCD": {"m": 72.987}, "MHL": {"m": 0.194}, "AFG": {"x": 0.741, "m": 1.643}, "VGB": {"m": 8.217}, "GRC": {"m": 133.753}, "GRL": {"m": 1.023}, "IND": {"x": 1157799.438, "m": 34101.068}, "VCT": {"m": 21.266}, "VNM": {"x": 592325.875, "m": 11214.362}, "NOR": {"x": 1443.162, "m": 6387.527}, "CZE": {"m": 953.29}, "FJI": {"x": 2.605, "m": 0.033}, "HND": {"m": 1.927}, "MUS": {"m": 11.141}, "DOM": {"m": 4.054}, "LUX": {"m": 24.715}, "ISR": {"x": 6.262, "m": 20.608}, "PER": {"m": 10.715}, "IDN": {"x": 459874.275, "m": 81526.84}, "COG": {"m": 36.064}, "ISL": {"m": 59.323}, "UMI": {"m": 169.635}, "COL": {"m": 27.835}, "SER": {"m": 0.098}, "MDG": {"m": 39.131}, "ECU": {"m": 3.204}, "SEN": {"m": 8.43}, "MDV": {"m": 56.861}, "ASM": {"m": 5.463}, "CUW": {"x": 0.721}, "FRA": {"x": 3326.167, "m": 31038.614}, "UNS": {"x": 79.176, "m": 18568.388}, "GTM": {"m": 36.743}, "DNK": {"x": 369.087, "m": 5196.439}, "AUS": {"x": 968684.908, "m": 50873.196}, "AUT": {"x": 3.388, "m": 1831.823}, "VEN": {"x": 2.385}, "KEN": {"x": 2.404, "m": 0.006}, "LAO": {"x": 0.561, "m": 0.821}, "TUR": {"x": 0.793, "m": 1360.908}, "ALB": {"x": 9.618}, "OMN": {"x": 602.297, "m": 467.382}, "MMR": {"x": 27.054, "m": 183.708}, "TUN": {"m": 1.479}, "RUS": {"x": 37.074}, "MEX": {"x": 5.481, "m": 6396.112}, "BRA": {"x": 50.807, "m": 7970.534}, "USA": {"x": 95109.169, "m": 278776.081}, "SWE": {"x": 0.242, "m": 4027.944}, "UKR": {"m": 4.465}, "GNB": {"m": 0.477}, "SWZ": {"m": 1157.415}, "CAN": {"x": 944.626, "m": 12299.335}, "KOR": {"x": 2046767.256, "m": 135468.059}, "AIA": {"m": 2.736}, "SVK": {"m": 1841.282}, "CYP": {"m": 85.415}, "SGP": {"x": 233200.173, "m": 837938.091}, "SOM": {"m": 19.971}, "POL": {"m": 479.087}, "KWT": {"x": 96.79, "m": 3.653}, "TGO": {"m": 2.66}, "ESP": {"x": 0.315, "m": 3642.615}, "IRQ": {"m": 0.003}, "MLI": {"m": 15.861}, "IRL": {"m": 3852.435}, "IRN": {"x": 9.099, "m": 407.811}, "SLE": {"m": 6.55}, "SLB": {"m": 0.085}, "NZL": {"x": 661385.154, "m": 9085.932}, "JPN": {"x": 5737858.907, "m": 268016.725}, "ARE": {"x": 956.131, "m": 6296.16}, "ARG": {"x": 0.04, "m": 291.937}, "BHS": {"m": 0.452}, "BHR": {"x": 1.297, "m": 3.586}, "PNG": {"x": 914.737, "m": 1.412}, "CUB": {"m": 0.335}}, "1968": {"USA": {"x": 0.0, "m": 11695.168}, "ISR": {"m": 10.475}, "SWE": {"m": 85.379}, "DEU": {"x": 6.942, "m": 1574.014}, "LKA": {"x": 0.0, "m": 40.325}, "IDN": {"x": 0.0, "m": 100.071}, "VUT": {"m": 0.622}, "GBR": {"x": 11.13, "m": 16569.736}, "CAN": {"m": 165.749}, "KOR": {"m": 8.937}, "CHE": {"m": 93.99}, "CYP": {"m": 1.342}, "MYS": {"x": 89249.912, "m": 3525.371}, "SGP": {"x": 158.84, "m": 9501.938}, "HUN": {"m": 0.835}, "PRK": {"m": 1.519}, "PRT": {"m": 7.233}, "POL": {"m": 2.701}, "TTO": {"m": 2.875}, "KHM": {"m": 14.687}, "HKG": {"x": 10.302, "m": 2877.251}, "NLD": {"x": 0.0, "m": 1790.758}, "FRA": {"m": 894.973}, "UNS": {"x": 8.135, "m": 1554.54}, "BLX": {"m": 615.414}, "AUT": {"m": 142.595}, "ESP": {"m": 17.665}, "ZMB": {"m": 0.661}, "IRQ": {"m": 0.977}, "DNK": {"m": 316.642}, "PAK": {"x": 0.0, "m": 4.911}, "AUS": {"x": 1.378, "m": 1903.38}, "MMR": {"x": 0.0, "m": 3.598}, "CHN": {"m": 2624.155}, "RUS": {"m": 19.942}, "FIN": {"m": 19.456}, "THA": {"m": 3038.972}, "NZL": {"m": 26.915}, "JPN": {"x": 0.0, "m": 7046.166}, "ZAF": {"m": 41.014}, "PHL": {"m": 5.893}, "ITA": {"x": 0.0, "m": 497.209}, "ARG": {"m": 11.468}, "IND": {"m": 139.878}, "OAS": {"x": 1.293, "m": 463.352}, "BHR": {"m": 0.821}, "MEX": {"m": 2.098}, "NOR": {"m": 19.563}, "CZE": {"m": 4.479}}, "1969": {"USA": {"m": 10462.177}, "ISR": {"m": 26.555}, "SWE": {"m": 112.619}, "DEU": {"x": 9.752, "m": 1140.227}, "LKA": {"m": 46.213}, "IDN": {"x": 0.0, "m": 150.963}, "GBR": {"x": 1.866, "m": 16350.951}, "CAN": {"m": 31.198}, "KOR": {"m": 17.283}, "CHE": {"m": 57.831}, "CYP": {"m": 1.635}, "SER": {"m": 1.021}, "SGP": {"x": 271.726, "m": 11005.935}, "HUN": {"m": 1.015}, "PRK": {"m": 1.872}, "PRT": {"m": 6.23}, "POL": {"m": 5.201}, "KHM": {"m": 4.188}, "HKG": {"x": 20.879, "m": 2996.634}, "NLD": {"x": 5.138, "m": 1666.971}, "SVR": {"m": 1.442}, "FRA": {"m": 611.84}, "UNS": {"x": 4.733, "m": 1483.408}, "BLX": {"m": 78.053}, "AUT": {"m": 55.715}, "ESP": {"m": 10.718}, "ZMB": {"m": 11.237}, "IRQ": {"m": 1.245}, "DNK": {"m": 414.813}, "PAK": {"m": 80.697}, "AUS": {"x": 0.0, "m": 3412.705}, "MMR": {"m": 8.549}, "CHN": {"m": 2951.48}, "RUS": {"m": 24.884}, "FIN": {"m": 15.686}, "THA": {"x": 0.0, "m": 2584.325}, "NZL": {"m": 47.413}, "MOZ": {"x": 0.0}, "JPN": {"x": 0.0, "m": 9189.793}, "ZAF": {"m": 33.332}, "PHL": {"x": 0.0, "m": 12.469}, "ITA": {"m": 511.113}, "ARG": {"m": 10.666}, "IND": {"m": 285.194}, "OAS": {"m": 624.306}, "SDN": {"m": 1.605}, "MYS": {"x": 84666.654, "m": 4874.019}, "NOR": {"m": 19.245}, "CZE": {"m": 9.684}}, "1991": {"DZA": {"m": 13.617}, "EGY": {"m": 10.745}, "BGD": {"m": 17.653}, "NGA": {"m": 3.616}, "MUS": {"m": 3.855}, "DOM": {"m": 15.904}, "ISR": {"m": 34.441}, "SWE": {"m": 5934.244}, "DEU": {"x": 689.216, "m": 51247.776}, "PER": {"m": 15.889}, "LKA": {"m": 17.226}, "IDN": {"x": 31.429, "m": 19948.756}, "BGR": {"m": 10.829}, "UNS": {"x": 2.237, "m": 3368.896}, "GBR": {"x": 822.495, "m": 85070.776}, "CAN": {"x": 115.327, "m": 4507.373}, "ISL": {"m": 1.253}, "KOR": {"x": 276121.012, "m": 7625.068}, "COL": {"m": 0.531}, "CHE": {"x": 12.781, "m": 1935.198}, "JOR": {"m": 14.424}, "CYP": {"m": 6.742}, "MYS": {"x": 1880.476, "m": 116208.176}, "SYR": {"m": 4.036}, "NRU": {"m": 0.901}, "HUN": {"x": 9.176, "m": 104.322}, "MDG": {"m": 24.411}, "PRK": {"m": 2.203}, "PRT": {"m": 127.496}, "POL": {"m": 116.724}, "NLD": {"x": 1612.403, "m": 31589.24}, "USA": {"x": 26392.814, "m": 165191.44}, "HKG": {"x": 0.0, "m": 21372.224}, "SAU": {"m": 91.583}, "NPL": {"x": 0.0, "m": 4.296}, "VNM": {"m": 49.406}, "FRA": {"x": 506.41, "m": 12513.358}, "ROM": {"m": 111.501}, "SER": {"m": 20.852}, "BLX": {"m": 4542.749}, "AUT": {"x": 65.658, "m": 2725.383}, "ESP": {"x": 144.964, "m": 1662.964}, "IRQ": {"m": 0.512}, "AFG": {"m": 4.313}, "CHL": {"m": 138.352}, "DNK": {"x": 0.0, "m": 32602.974}, "PAK": {"x": 0.0, "m": 232.783}, "NOR": {"x": 452.911, "m": 416.566}, "AUS": {"x": 70358.799, "m": 26387.34}, "MMR": {"x": 0.0, "m": 84.783}, "IRL": {"m": 181.292}, "CHN": {"x": 3813.026, "m": 34738.896}, "IRN": {"m": 119.59}, "RUS": {"m": 36.094}, "PNG": {"m": 0.913}, "FIN": {"m": 6128.774}, "URY": {"m": 204.978}, "THA": {"x": 220087.948, "m": 32413.998}, "NZL": {"x": 5563.608, "m": 3395.02}, "MOZ": {"m": 354.739}, "JPN": {"x": 1674672.581, "m": 190551.024}, "TUR": {"m": 28.591}, "PHL": {"x": 103970.829, "m": 1541.675}, "OMN": {"x": 0.628, "m": 167.446}, "ITA": {"x": 103.457, "m": 53695.54}, "SGP": {"x": 152897.52, "m": 266407.392}, "MAC": {"m": 12.724}, "ARE": {"x": 0.0, "m": 846.517}, "ARG": {"m": 1215.271}, "IND": {"x": 2.199, "m": 1792.309}, "OAS": {"x": 71428.846, "m": 16200.016}, "SDN": {"m": 1.136}, "BHR": {"x": 0.0, "m": 6.898}, "MEX": {"x": 23.332, "m": 71.138}, "BRA": {"m": 1641.134}, "CZE": {"m": 175.708}}, "1990": {"DZA": {"m": 14.204}, "EGY": {"m": 6.352}, "BGD": {"x": 0.0, "m": 2.911}, "NGA": {"x": 0.0}, "MUS": {"m": 1.907}, "DOM": {"m": 23.39}, "ISR": {"m": 24.535}, "SWE": {"x": 42.355, "m": 4150.312}, "DEU": {"x": 122.146, "m": 39378.644}, "PER": {"m": 43.447}, "LKA": {"m": 24.695}, "IDN": {"x": 16.557, "m": 18651.18}, "BGR": {"m": 19.518}, "GBR": {"x": 885.409, "m": 65404.464}, "CAN": {"x": 104.693, "m": 1210.369}, "ROM": {"m": 32.998}, "KOR": {"x": 273993.344, "m": 6190.317}, "COL": {"m": 0.768}, "CHE": {"x": 0.0, "m": 3721.719}, "CYP": {"m": 7.057}, "MYS": {"x": 1281.892, "m": 102736.92}, "SGP": {"x": 126122.11, "m": 259005.504}, "HUN": {"m": 48.382}, "MDG": {"m": 16.059}, "TZA": {"x": 0.0, "m": 0.798}, "PRT": {"m": 72.373}, "POL": {"m": 39.213}, "KWT": {"m": 29.27}, "USA": {"x": 73264.397, "m": 152862.336}, "BMU": {"x": 0.0}, "HKG": {"x": 45.535, "m": 15632.962}, "SAU": {"m": 83.01}, "NLD": {"x": 496.55, "m": 20384.612}, "NPL": {"x": 0.0, "m": 5.697}, "VNM": {"m": 23.167}, "FRA": {"x": 233.473, "m": 14347.858}, "UNS": {"x": 1.535, "m": 2056.351}, "SER": {"m": 139.173}, "BLX": {"x": 185.203, "m": 2727.772}, "AUT": {"m": 1649.834}, "ESP": {"m": 1620.109}, "ZMB": {"x": 0.0}, "IRQ": {"m": 2.319}, "GRC": {"m": 6.261}, "CHL": {"m": 305.819}, "DNK": {"x": 0.0, "m": 7826.477}, "PAK": {"x": 0.0, "m": 184.618}, "NOR": {"x": 142.757, "m": 575.628}, "AUS": {"x": 28724.087, "m": 25761.668}, "MMR": {"x": 0.0, "m": 42.876}, "IRL": {"m": 808.666}, "CHN": {"x": 3183.244, "m": 27031.336}, "IRN": {"m": 61.023}, "RUS": {"m": 3.782}, "PNG": {"x": 0.0}, "FIN": {"x": 18.033, "m": 1058.753}, "URY": {"m": 119.237}, "THA": {"x": 170564.201, "m": 37188.54}, "NZL": {"x": 0.0, "m": 3352.641}, "MOZ": {"m": 126.797}, "MAR": {"m": 1.225}, "JPN": {"x": 1285547.243, "m": 145747.104}, "TUR": {"x": 0.0, "m": 38.162}, "PHL": {"x": 108217.351, "m": 1535.324}, "OMN": {"x": 0.827, "m": 29.694}, "ITA": {"x": 0.0, "m": 21445.62}, "SYR": {"m": 4.498}, "MAC": {"m": 36.665}, "ARE": {"x": 0.0, "m": 83.734}, "TUN": {"x": 0.0, "m": 0.881}, "ARG": {"m": 1234.481}, "IND": {"x": 0.0, "m": 1259.84}, "OAS": {"x": 74560.818, "m": 11179.953}, "MEX": {"m": 74.3}, "BRA": {"m": 1162.303}, "CZE": {"m": 51.716}}, "1993": {"EGY": {"m": 58.494}, "BGD": {"m": 6.44}, "BGR": {"m": 16.243}, "OAS": {"x": 63505.112, "m": 16440.245}, "PAK": {"m": 177.178}, "MYS": {"x": 450.491, "m": 150739.408}, "PRK": {"m": 192.329}, "PRT": {"m": 211.853}, "HKG": {"m": 29809.036}, "SAU": {"m": 704.466}, "CHE": {"m": 893.787}, "MRT": {"m": 1.126}, "CHL": {"m": 226.094}, "CHN": {"m": 22651.14}, "JAM": {"m": 6.109}, "FIN": {"m": 328.331}, "URY": {"m": 29.068}, "THA": {"x": 214691.088, "m": 29213.784}, "NPL": {"m": 1183.244}, "YEM": {"m": 27.216}, "PHL": {"x": 48669.668, "m": 2245.047}, "ZAF": {"m": 596.82}, "SYR": {"m": 2.752}, "MAC": {"m": 3.147}, "DEU": {"m": 216806.608}, "LKA": {"m": 45.307}, "GBR": {"x": 64.643, "m": 77289.632}, "GUY": {"m": 1.38}, "ITA": {"m": 94574.776}, "ROM": {"m": 59.968}, "HUN": {"m": 143.776}, "NLD": {"m": 51955.704}, "BLX": {"m": 25990.476}, "AFG": {"m": 1.272}, "BDI": {"m": 90.243}, "VGB": {"m": 1.052}, "GRC": {"m": 0.625}, "IND": {"m": 2777.409}, "VNM": {"m": 196.205}, "NOR": {"m": 176.71}, "CZE": {"m": 76.77}, "ATG": {"m": 6.539}, "FJI": {"m": 1.661}, "MUS": {"m": 1.558}, "DOM": {"m": 8.644}, "ISR": {"m": 40.706}, "IDN": {"m": 54713.992}, "VUT": {"m": 2.717}, "SUR": {"m": 0.879}, "ISL": {"m": 0.841}, "COL": {"m": 0.722}, "SER": {"m": 13.67}, "FRA": {"m": 11995.104}, "UNS": {"x": 1.336, "m": 2735.395}, "DNK": {"m": 5612.532}, "AUS": {"x": 17217.51, "m": 45559.456}, "AUT": {"m": 1580.07}, "TUR": {"m": 32.838}, "OMN": {"m": 5.966}, "MMR": {"m": 83.607}, "TUN": {"m": 1.266}, "RUS": {"m": 94.348}, "MEX": {"m": 29.262}, "BRA": {"m": 1325.039}, "USA": {"x": 8642.774, "m": 457020.896}, "SWE": {"m": 3660.04}, "CAN": {"x": 1.156, "m": 1450.954}, "USP": {"m": 65.138}, "KOR": {"x": 241957.68, "m": 15790.631}, "MWI": {"m": 11.922}, "CYP": {"m": 30.957}, "SGP": {"x": 173746.336, "m": 310754.048}, "POL": {"m": 53.281}, "ESP": {"m": 1645.679}, "MLI": {"m": 174.102}, "IRL": {"m": 493.455}, "IRN": {"m": 155.531}, "ABW": {"m": 2.678}, "SLE": {"m": 0.641}, "NZL": {"m": 7136.148}, "JPN": {"x": 1324999.552, "m": 170477.888}, "ARE": {"m": 1462.534}, "ARG": {"m": 316.16}, "BHS": {"m": 3.638}, "BHR": {"m": 17.074}, "UGA": {"m": 9.485}}, "1992": {"DZA": {"m": 3.124}, "EGY": {"m": 688.278}, "BGD": {"m": 7.873}, "BGR": {"m": 49.737}, "OAS": {"x": 68669.928, "m": 18840.044}, "PAK": {"m": 207.091}, "JOR": {"m": 43.591}, "MYS": {"x": 2510.434, "m": 135068.032}, "IOT": {"m": 63.211}, "PRK": {"m": 113.743}, "TZA": {"m": 1.402}, "PRT": {"m": 126.576}, "HKG": {"x": 143.441, "m": 27461.102}, "SAU": {"m": 869.745}, "LBN": {"m": 0.673}, "CHE": {"m": 1600.008}, "MRT": {"m": 0.63}, "CHL": {"m": 112.925}, "CHN": {"x": 4592.975, "m": 30664.356}, "JAM": {"m": 8.439}, "GIN": {"m": 10.736}, "FIN": {"m": 359.408}, "URY": {"m": 23.46}, "THA": {"x": 214766.128, "m": 27779.668}, "NPL": {"m": 2.195}, "MAR": {"m": 0.537}, "PHL": {"x": 88618.112, "m": 2983.118}, "ZAF": {"m": 733.069}, "MAC": {"m": 10.532}, "NGA": {"m": 5.063}, "DEU": {"x": 30.372, "m": 59824.992}, "LKA": {"m": 15.47}, "GBR": {"x": 366.263, "m": 90498.784}, "GUY": {"m": 8.257}, "ITA": {"m": 82705.848}, "ROM": {"m": 78.483}, "HUN": {"m": 131.72}, "NLD": {"x": 20.737, "m": 21392.34}, "BMU": {"m": 26.522}, "TCD": {"m": 187.084}, "MLI": {"m": 69.236}, "BLX": {"m": 5345.789}, "BLZ": {"m": 3.83}, "AFG": {"m": 17.821}, "VGB": {"m": 0.547}, "GRD": {"m": 2.807}, "GRC": {"m": 0.503}, "GRL": {"m": 8.72}, "MOZ": {"m": 146.551}, "BRB": {"m": 2.177}, "IND": {"m": 2301.775}, "BTN": {"m": 20.131}, "VNM": {"m": 146.968}, "NOR": {"x": 226.614, "m": 456.584}, "CZE": {"m": 125.94}, "ATG": {"m": 1.487}, "HND": {"m": 0.625}, "MUS": {"m": 2.881}, "DOM": {"m": 9.52}, "ISR": {"m": 611.691}, "IDN": {"x": 18.404, "m": 25500.254}, "SUR": {"m": 14.601}, "ISL": {"m": 24.021}, "GLP": {"m": 3.382}, "COL": {"m": 1.457}, "SER": {"m": 21.199}, "MDG": {"m": 1.27}, "ESH": {"m": 2.059}, "FRA": {"m": 38217.296}, "UNS": {"x": 2.325, "m": 1268.943}, "DNK": {"x": 17.01, "m": 6379.732}, "AUS": {"x": 53196.832, "m": 29443.714}, "AUT": {"m": 1384.509}, "TUR": {"m": 566.377}, "OMN": {"m": 185.761}, "MMR": {"m": 36.91}, "TUN": {"m": 50.668}, "RUS": {"m": 41.005}, "MEX": {"m": 68.343}, "BRA": {"m": 1502.614}, "USA": {"x": 19559.202, "m": 272347.904}, "SWE": {"m": 4338.441}, "TON": {"m": 0.642}, "CAN": {"x": 294.908, "m": 1996.611}, "USP": {"m": 14.425}, "KOR": {"x": 289702.592, "m": 12491.252}, "MWI": {"m": 7.791}, "CYP": {"m": 6.426}, "SGP": {"x": 235152.608, "m": 328551.872}, "POL": {"m": 35.108}, "ESP": {"m": 1273.153}, "MTQ": {"m": 43.919}, "IRL": {"m": 529.02}, "IRN": {"m": 73.616}, "ABW": {"m": 3.774}, "SLE": {"m": 2.331}, "NZL": {"m": 6046.457}, "JPN": {"x": 1323329.408, "m": 229257.248}, "ARE": {"m": 1450.488}, "ARG": {"m": 417.74}, "BHS": {"m": 5.273}, "BHR": {"m": 48.962}, "UGA": {"m": 3.723}, "PNG": {"m": 8.935}}, "1994": {"DZA": {"m": 4.791}, "QAT": {"m": 14.69}, "EGY": {"m": 92.846}, "BGD": {"m": 149.362}, "BGR": {"m": 0.814}, "OAS": {"x": 59541.44, "m": 29325.934}, "PAK": {"m": 269.507}, "PAN": {"m": 1.237}, "JOR": {"m": 36.09}, "MYS": {"x": 23224.924, "m": 244533.76}, "PRK": {"m": 220.927}, "PRT": {"m": 281.502}, "KHM": {"m": 3.565}, "HKG": {"x": 14.359, "m": 19488.664}, "SAU": {"m": 333.998}, "LBN": {"m": 70.213}, "CHE": {"x": 2.013, "m": 29406.27}, "CHL": {"m": 445.947}, "CHN": {"m": 33341.032}, "JAM": {"m": 7.621}, "GIN": {"m": 5.964}, "FIN": {"x": 3.73, "m": 467.745}, "URY": {"m": 20.259}, "THA": {"x": 245232.192, "m": 58407.608}, "SYC": {"m": 2.884}, "NPL": {"m": 4.592}, "MAR": {"m": 5.847}, "PHL": {"x": 34514.768, "m": 2527.907}, "ZAF": {"m": 430.021}, "SYR": {"m": 1.249}, "MAC": {"m": 9.789}, "DEU": {"m": 77057.968}, "LKA": {"m": 29.037}, "GBR": {"x": 707.484, "m": 130023.912}, "MWI": {"m": 21.058}, "ITA": {"m": 37554.34}, "ROM": {"m": 41.23}, "HUN": {"m": 100.182}, "NLD": {"m": 41510.224}, "TCA": {"m": 3.447}, "BLX": {"m": 3818.84}, "BLZ": {"m": 3.376}, "AFG": {"m": 31.234}, "BDI": {"m": 30.055}, "GRD": {"m": 15.003}, "GRC": {"m": 113.249}, "BRB": {"m": 19.511}, "IND": {"m": 3856.511}, "VNM": {"m": 174.254}, "NOR": {"m": 6312.961}, "CZE": {"m": 515.166}, "ATG": {"m": 26.94}, "FJI": {"m": 13.798}, "HND": {"m": 1.263}, "MUS": {"m": 2.723}, "ISR": {"m": 41.685}, "PER": {"m": 1.074}, "IDN": {"m": 67195.92}, "VUT": {"m": 1.561}, "SUR": {"m": 1.996}, "GLP": {"m": 1.271}, "SER": {"m": 47.295}, "MDG": {"m": 0.71}, "ECU": {"m": 3.214}, "FRA": {"m": 16122.103}, "UNS": {"x": 1.844, "m": 1179.76}, "WLF": {"m": 1.018}, "GTM": {"m": 5.03}, "DNK": {"x": 34.281, "m": 17281.78}, "AUS": {"x": 83.795, "m": 65092.72}, "AUT": {"m": 2944.21}, "KEN": {"m": 0.743}, "TUR": {"m": 42.7}, "OMN": {"m": 132.192}, "MMR": {"m": 76.882}, "TUN": {"m": 20.118}, "RUS": {"m": 2.407}, "MEX": {"m": 59.865}, "BRA": {"m": 555.644}, "BAT": {"m": 1.669}, "USA": {"x": 23285.818, "m": 212365.936}, "SWE": {"m": 12201.613}, "CAN": {"x": 309.253, "m": 3179.534}, "USP": {"m": 194.493}, "KOR": {"x": 306640.992, "m": 17674.12}, "CYP": {"m": 31.727}, "SGP": {"x": 196821.168, "m": 521371.264}, "POL": {"m": 217.687}, "TGO": {"m": 23.925}, "ESP": {"x": 17.342, "m": 2538.143}, "IRQ": {"m": 6.449}, "MLI": {"m": 575.634}, "IRL": {"m": 474.677}, "IRN": {"m": 366.325}, "ABW": {"m": 6.371}, "SLE": {"m": 1.39}, "NZL": {"m": 17235.042}, "JPN": {"x": 1219872.512, "m": 189035.712}, "ARE": {"m": 3620.357}, "ARG": {"m": 395.86}, "BHS": {"m": 8.53}, "BHR": {"x": 1.623, "m": 55.506}}, "1997": {"QAT": {"x": 32.726}, "EGY": {"x": 24.598, "m": 182.505}, "BGD": {"m": 44.03}, "BGR": {"m": 2.233}, "OAS": {"x": 71096.848, "m": 28132.44}, "GHA": {"m": 2.501}, "PAK": {"x": 14.742, "m": 559.559}, "JOR": {"x": 66.917, "m": 112.945}, "MYS": {"x": 74216.056, "m": 286390.112}, "PRK": {"x": 2.953, "m": 362.156}, "PRT": {"m": 74.66}, "KHM": {"x": 16.149, "m": 37.884}, "HKG": {"x": 693.482, "m": 76844.216}, "SAU": {"x": 34.062, "m": 504.093}, "LBN": {"m": 0.72}, "CHE": {"x": 75.053, "m": 11327.56}, "CHL": {"m": 248.727}, "CHN": {"x": 100.61, "m": 51902.824}, "LAO": {"x": 10.037}, "FIN": {"x": 0.869, "m": 375.491}, "THA": {"x": 297001.312, "m": 82884.48}, "SYC": {"m": 0.98}, "NPL": {"x": 8.105, "m": 12.535}, "MAR": {"m": 8.347}, "PHL": {"x": 821.588, "m": 9550.993}, "ZAF": {"m": 1252.55}, "SYR": {"x": 209.5}, "MAC": {"m": 102.406}, "DEU": {"x": 9680.296, "m": 126162.608}, "LKA": {"x": 15.065, "m": 345.203}, "GBR": {"x": 15366.67, "m": 128080.928}, "MWI": {"m": 11.177}, "ITA": {"x": 27.43, "m": 49243.232}, "ROM": {"m": 88.803}, "HUN": {"x": 0.501, "m": 333.123}, "NLD": {"x": 3138.589, "m": 25590.796}, "BLX": {"x": 8.742, "m": 4367.97}, "BLZ": {"m": 107.786}, "AFG": {"m": 82.385}, "BDI": {"m": 219.075}, "GRC": {"m": 89.811}, "IND": {"x": 39.811, "m": 12969.807}, "VNM": {"x": 300.647, "m": 481.29}, "NOR": {"x": 1241.645, "m": 424.958}, "CZE": {"x": 1.166, "m": 154.063}, "ATG": {"m": 17.888}, "FJI": {"m": 0.716}, "MUS": {"x": 235.074}, "DOM": {"m": 0.712}, "ISR": {"m": 23.095}, "PER": {"m": 58.821}, "IDN": {"x": 4364.971, "m": 39279.52}, "ISL": {"m": 0.668}, "COL": {"x": 97.613, "m": 0.922}, "MDG": {"m": 0.93}, "FRA": {"x": 2528.644, "m": 24998.724}, "UNS": {"x": 228.094, "m": 5782.111}, "GTM": {"m": 3.742}, "DNK": {"x": 257.435, "m": 5146.665}, "AUS": {"x": 18502.576, "m": 55218.16}, "AUT": {"m": 872.266}, "KEN": {"m": 17.928}, "TUR": {"m": 16617.509}, "ALB": {"m": 7.468}, "OMN": {"x": 867.447, "m": 110.172}, "MMR": {"x": 48.659, "m": 1279.511}, "TUN": {"m": 11.654}, "RUS": {"m": 150.511}, "MEX": {"m": 66.306}, "BRA": {"m": 550.724}, "USA": {"x": 65189.852, "m": 211046.352}, "SWE": {"x": 64.24, "m": 8791.292}, "CAN": {"x": 679.213, "m": 5986.212}, "USP": {"m": 3.231}, "KOR": {"x": 482272.224, "m": 37987.544}, "CYP": {"m": 8.538}, "SGP": {"x": 176243.152, "m": 539996.928}, "POL": {"m": 130.842}, "KWT": {"m": 5.025}, "ESP": {"m": 3282.588}, "IRL": {"m": 696.58}, "IRN": {"x": 23.102, "m": 425.594}, "NZL": {"x": 19312.916, "m": 8175.008}, "JPN": {"x": 1410484.608, "m": 235864.56}, "ARE": {"x": 1419.443, "m": 6626.346}, "ARG": {"x": 13.383, "m": 1340.18}, "BHS": {"m": 0.941}, "BHR": {"m": 2.71}}, "1978": {"QAT": {"x": 0.0}, "EGY": {"m": 2.302}, "USA": {"x": 165538.032, "m": 41931.636}, "ISR": {"m": 29.115}, "SWE": {"m": 630.124}, "DEU": {"m": 6436.245}, "LKA": {"x": 0.0, "m": 39.632}, "IDN": {"m": 289.624}, "BGR": {"m": 1.231}, "GBR": {"x": 15.797, "m": 29380.204}, "CAN": {"m": 216.636}, "USP": {"m": 1.037}, "KOR": {"m": 852.355}, "MNG": {"m": 0.674}, "PAN": {"m": 1.476}, "CHE": {"m": 286.06}, "CYP": {"m": 2.503}, "MYS": {"x": 428.684, "m": 14544.012}, "SGP": {"x": 84076.649, "m": 60640.856}, "HUN": {"m": 2.84}, "PRK": {"m": 19.992}, "PRT": {"m": 55.972}, "POL": {"m": 100.06}, "NLD": {"x": 0.0, "m": 2312.434}, "CHN": {"m": 8199.398}, "HKG": {"x": 0.0, "m": 4528.206}, "SAU": {"x": 0.0}, "LBN": {"m": 1.056}, "CUW": {"m": 0.736}, "VNM": {"m": 0.723}, "FRA": {"x": 0.0, "m": 3191.791}, "UNS": {"x": 4.421, "m": 6314.053}, "SER": {"m": 2.736}, "BLX": {"m": 825.533}, "ESP": {"m": 166.068}, "IRQ": {"m": 4.073}, "AFG": {"m": 0.696}, "CHL": {"m": 2.182}, "DNK": {"m": 1099.169}, "PAK": {"m": 31.227}, "ROM": {"m": 47.904}, "AUS": {"x": 0.0, "m": 4883.962}, "MMR": {"m": 22.197}, "IRL": {"m": 0.809}, "AUT": {"m": 95.522}, "IRN": {"m": 1.281}, "NPL": {"m": 1.692}, "FIN": {"m": 837.544}, "THA": {"x": 22634.046, "m": 7698.443}, "NZL": {"m": 1415.261}, "KEN": {"x": 0.0, "m": 30.254}, "MAR": {"m": 1.419}, "JPN": {"x": 1343089.158, "m": 66799.124}, "ZAF": {"x": 85324.68, "m": 4.218}, "PHL": {"x": 1401.225, "m": 2395.18}, "ITA": {"x": 0.0, "m": 1673.124}, "MAC": {"m": 0.583}, "NOR": {"m": 190.018}, "ARG": {"m": 63.889}, "IND": {"m": 1972.393}, "OAS": {"x": 72711.856, "m": 4795.333}, "RUS": {"m": 69.759}, "CZE": {"m": 28.598}, "MEX": {"m": 31.612}, "BRA": {"m": 585.075}, "CUB": {"m": 2.593}}, "1977": {"GRC": {"m": 30.816}, "NGA": {"x": 0.0}, "USA": {"x": 148555.099, "m": 58203.608}, "ISR": {"m": 20.955}, "MOZ": {"m": 2.422}, "SWE": {"m": 520.656}, "DEU": {"m": 11356.513}, "LKA": {"x": 0.0, "m": 26.909}, "GNB": {"m": 8.27}, "BGR": {"m": 2.006}, "GBR": {"x": 1.709, "m": 32899.096}, "CAN": {"x": 0.0, "m": 228.882}, "ISL": {"m": 0.952}, "KOR": {"m": 435.307}, "PAN": {"m": 1.819}, "CHE": {"m": 419.803}, "CYP": {"m": 1.637}, "MYS": {"x": 40741.308, "m": 14334.887}, "SGP": {"x": 58556.039, "m": 47776.536}, "HUN": {"m": 69.756}, "PRK": {"m": 27.427}, "PRT": {"m": 47.478}, "POL": {"m": 23.464}, "USP": {"m": 1.422}, "NLD": {"x": 0.0, "m": 7908.046}, "CHN": {"m": 6917.859}, "HKG": {"x": 16.32, "m": 4148.983}, "NPL": {"m": 0.62}, "VNM": {"m": 0.599}, "FRA": {"x": 1002.887, "m": 2821.945}, "UNS": {"x": 3.731, "m": 4851.594}, "SER": {"m": 2.275}, "BLX": {"x": 0.0, "m": 1197.855}, "AUT": {"x": 0.0, "m": 200.364}, "ESP": {"m": 173.271}, "IRQ": {"x": 0.0, "m": 0.775}, "CHL": {"x": 0.0, "m": 1.066}, "DNK": {"m": 1148.515}, "PAK": {"m": 45.004}, "NOR": {"m": 260.793}, "AUS": {"x": 0.0, "m": 4992.996}, "MMR": {"x": 0.0, "m": 36.37}, "IRL": {"m": 1.268}, "CUB": {"m": 1.355}, "IRN": {"m": 2.22}, "RUS": {"m": 89.701}, "GIN": {"m": 0.572}, "GRL": {"m": 0.605}, "FIN": {"m": 162.362}, "THA": {"x": 11946.613, "m": 5937.711}, "NZL": {"m": 951.013}, "IDN": {"m": 235.296}, "MAR": {"m": 0.736}, "COD": {"m": 260.522}, "JPN": {"x": 1245836.658, "m": 59149.896}, "ZAF": {"x": 58282.696, "m": 6.478}, "PHL": {"x": 0.0, "m": 1558.786}, "OMN": {"x": 0.0}, "ITA": {"x": 0.0, "m": 1308.057}, "SYR": {"m": 0.91}, "ARE": {"m": 4.814}, "ARG": {"m": 46.148}, "IND": {"m": 980.82}, "OAS": {"x": 47930.057, "m": 3414.623}, "ROM": {"m": 18.689}, "MEX": {"m": 14.06}, "BRA": {"m": 83.047}, "CZE": {"m": 43.775}}, "1998": {"QAT": {"x": 36.173}, "EGY": {"x": 97.324, "m": 47.969}, "BGD": {"x": 12.35, "m": 33.742}, "OAS": {"x": 44934.048, "m": 20111.956}, "GHA": {"m": 5.967}, "PAK": {"x": 45.322, "m": 349.386}, "JOR": {"m": 512.41}, "MYS": {"x": 19162.716, "m": 264537.392}, "IOT": {"m": 4.118}, "PRK": {"m": 2904.49}, "TZA": {"m": 0.981}, "PRT": {"m": 1.578}, "KHM": {"x": 0.88}, "HKG": {"x": 4038.528, "m": 67739.64}, "SAU": {"x": 31.999, "m": 299.313}, "LBN": {"x": 31.657, "m": 11.934}, "CHE": {"x": 1329.577, "m": 9177.999}, "MRT": {"x": 96.038}, "CHL": {"m": 116.207}, "CHN": {"x": 19.23, "m": 22953.302}, "FIN": {"m": 315.006}, "THA": {"x": 140832.784, "m": 67915.92}, "SYC": {"m": 0.542}, "NPL": {"x": 35.473, "m": 287.209}, "MAR": {"x": 1.551, "m": 1.489}, "YEM": {"x": 13.712}, "PHL": {"x": 452.142, "m": 5326.406}, "ZAF": {"m": 920.138}, "SYR": {"x": 406.405, "m": 115.422}, "MAC": {"m": 19.448}, "NGA": {"x": 14.646}, "DEU": {"x": 12884.63, "m": 49551.792}, "LKA": {"x": 143.768, "m": 386.659}, "GBR": {"x": 15512.846, "m": 103844.648}, "MWI": {"m": 2.099}, "ITA": {"x": 2068.748, "m": 28472.774}, "ROM": {"m": 36.534}, "HUN": {"m": 166.316}, "NLD": {"x": 14098.377, "m": 17792.31}, "MNG": {"x": 27.603, "m": 0.595}, "BLX": {"m": 4023.406}, "BLZ": {"m": 41.204}, "AFG": {"m": 134.387}, "BDI": {"m": 35.321}, "GRC": {"m": 306.616}, "BRB": {"m": 13.137}, "IND": {"x": 267.113, "m": 15591.657}, "VNM": {"x": 700.095, "m": 648.343}, "NOR": {"x": 2890.093, "m": 304.256}, "CZE": {"m": 21.803}, "FJI": {"m": 2.078}, "MUS": {"m": 1.033}, "ISR": {"m": 16.982}, "PER": {"x": 70.599, "m": 19.404}, "IDN": {"x": 5224.742, "m": 52510.392}, "ISL": {"m": 0.556}, "COL": {"m": 5.907}, "FRA": {"x": 1991.505, "m": 18908.064}, "UNS": {"x": 169.866, "m": 5004.072}, "ZMB": {"m": 0.907}, "GTM": {"m": 2.914}, "DNK": {"x": 427.386, "m": 3005.19}, "AUS": {"x": 5310.407, "m": 58133.792}, "AUT": {"x": 6.532, "m": 1087.448}, "VEN": {"x": 49.183, "m": 20.383}, "KEN": {"m": 43.92}, "TUR": {"m": 1682.358}, "OMN": {"x": 222.489, "m": 41.292}, "MMR": {"x": 7.071, "m": 494.327}, "TUN": {"m": 1.009}, "RUS": {"m": 68.485}, "MEX": {"m": 70.917}, "BRA": {"m": 248.827}, "USA": {"x": 210408.24, "m": 235140.64}, "SWE": {"x": 36.982, "m": 5773.312}, "CAN": {"x": 985.238, "m": 6403.756}, "USP": {"m": 1.962}, "KOR": {"x": 413976.96, "m": 21983.976}, "CYP": {"x": 2.679, "m": 4.25}, "SGP": {"x": 181288.832, "m": 355816.736}, "POL": {"m": 65.39}, "KWT": {"m": 1.154}, "ESP": {"x": 2.438, "m": 2582.783}, "IRL": {"x": 5.36, "m": 1588.67}, "IRN": {"x": 6.197, "m": 368.166}, "ABW": {"m": 0.84}, "NZL": {"x": 927.058, "m": 5455.433}, "JPN": {"x": 1225411.84, "m": 100365.248}, "ARE": {"m": 2756.248}, "ARG": {"x": 103.925, "m": 1123.58}, "BHR": {"x": 2.029}, "PNG": {"x": 4.437, "m": 53.782}}, "1975": {"QAT": {"x": 0.0}, "EGY": {"m": 3.323}, "USA": {"x": 73321.255, "m": 61647.16}, "ISR": {"m": 116.501}, "SWE": {"m": 401.56}, "DEU": {"m": 7690.545}, "LKA": {"x": 0.0, "m": 9.31}, "IDN": {"x": 0.0, "m": 1922.975}, "BGR": {"m": 0.762}, "GBR": {"x": 0.0, "m": 32642.096}, "CAN": {"m": 218.962}, "COG": {"m": 251.835}, "KOR": {"x": 0.0, "m": 401.432}, "CHE": {"m": 452.114}, "CYP": {"m": 3.449}, "MYS": {"x": 46676.783, "m": 12202.776}, "SGP": {"x": 481.312, "m": 46160.308}, "HUN": {"m": 10.828}, "PRK": {"m": 42.122}, "PRT": {"m": 32.431}, "POL": {"m": 33.247}, "NLD": {"x": 0.0, "m": 12252.868}, "CHN": {"m": 4876.818}, "HKG": {"x": 14.0, "m": 2799.697}, "SAU": {"x": 0.0, "m": 0.824}, "CUW": {"m": 3.4}, "VNM": {"m": 4.505}, "FRA": {"x": 0.0, "m": 3054.422}, "UNS": {"x": 5.047, "m": 1007.584}, "SER": {"m": 0.52}, "BLX": {"m": 1145.048}, "ESP": {"m": 73.195}, "IRQ": {"m": 1.814}, "DNK": {"m": 1014.669}, "PAK": {"m": 50.8}, "ROM": {"m": 1.049}, "AUS": {"x": 0.0, "m": 4598.864}, "MMR": {"m": 33.649}, "IRL": {"m": 1.872}, "CUB": {"m": 2.677}, "NPL": {"m": 0.523}, "FIN": {"m": 18.606}, "THA": {"x": 0.0, "m": 5020.657}, "NZL": {"x": 0.0, "m": 433.257}, "MOZ": {"m": 0.938}, "MAR": {"m": 0.996}, "JPN": {"x": 806488.901, "m": 59674.984}, "ZAF": {"x": 76924.152, "m": 16.517}, "TUR": {"x": 0.0}, "PHL": {"m": 5019.672}, "OMN": {"x": 0.0}, "ITA": {"m": 1031.727}, "SYR": {"m": 51.623}, "UGA": {"m": 0.813}, "NOR": {"m": 274.088}, "ARG": {"m": 11.067}, "IND": {"x": 0.0, "m": 535.956}, "OAS": {"x": 18830.436, "m": 1845.269}, "RUS": {"m": 19.684}, "CZE": {"m": 38.732}, "MEX": {"m": 13.683}, "BRA": {"m": 50.565}, "AUT": {"m": 152.129}}, "1974": {"QAT": {"x": 0.0}, "EGY": {"x": 0.0, "m": 1.402}, "NGA": {"x": 0.0}, "USA": {"x": 50846.332, "m": 37575.456}, "ISR": {"m": 142.806}, "MOZ": {"m": 17.753}, "SWE": {"m": 188.016}, "DEU": {"x": 0.0, "m": 4041.728}, "LKA": {"x": 0.0, "m": 110.557}, "IDN": {"x": 0.0, "m": 228.738}, "GBR": {"x": 3.485, "m": 19986.944}, "CAN": {"x": 0.0, "m": 275.384}, "KOR": {"x": 0.0, "m": 1073.947}, "COL": {"m": 1.123}, "CHE": {"m": 288.978}, "CYP": {"m": 2.921}, "MYS": {"x": 65785.54, "m": 8380.529}, "SGP": {"x": 675.56, "m": 27944.508}, "HUN": {"m": 6.537}, "PRK": {"m": 7.291}, "PRT": {"x": 0.0, "m": 30.436}, "POL": {"m": 71.26}, "NLD": {"x": 0.0, "m": 7055.91}, "CHN": {"x": 149.129, "m": 5030.722}, "HKG": {"x": 43.741, "m": 2681.004}, "SAU": {"x": 0.0}, "LBN": {"m": 0.574}, "CUW": {"m": 4.3}, "FRA": {"m": 1516.46}, "UNS": {"x": 6.142, "m": 1679.872}, "SER": {"m": 12.399}, "BLX": {"m": 401.069}, "ESP": {"m": 48.204}, "IRQ": {"m": 0.882}, "DNK": {"m": 933.61}, "PAK": {"m": 34.862}, "ROM": {"m": 2.414}, "AUS": {"x": 0.0, "m": 3489.183}, "MMR": {"m": 26.339}, "AUT": {"m": 299.52}, "IRN": {"m": 0.993}, "RUS": {"m": 18.459}, "PNG": {"m": 3.314}, "FIN": {"m": 5.503}, "PYF": {"m": 0.797}, "THA": {"m": 7878.158}, "NZL": {"x": 0.0, "m": 377.461}, "KEN": {"m": 5.052}, "MAR": {"m": 0.537}, "COD": {"m": 356.302}, "JPN": {"x": 777443.321, "m": 50233.068}, "ZAF": {"x": 53007.908, "m": 23.67}, "PHL": {"m": 1928.45}, "ITA": {"m": 1375.762}, "NOR": {"m": 62.32}, "ARG": {"m": 0.547}, "IND": {"x": 0.0, "m": 603.902}, "OAS": {"x": 31223.192, "m": 1286.707}, "CZE": {"m": 40.406}, "MEX": {"m": 5.475}, "BRA": {"m": 26.693}, "CUB": {"m": 2.138}}, "1973": {"AGO": {"m": 915.341}, "USA": {"x": 20299.555, "m": 23255.204}, "ISR": {"m": 173.203}, "SWE": {"m": 168.732}, "DEU": {"m": 2812.323}, "LKA": {"x": 0.0, "m": 52.538}, "IDN": {"x": 0.0, "m": 165.817}, "GBR": {"x": 0.659, "m": 15429.55}, "CAN": {"m": 133.793}, "KOR": {"x": 0.0, "m": 89.627}, "CHE": {"m": 303.244}, "CYP": {"m": 1.634}, "MYS": {"x": 31921.116, "m": 8065.813}, "SGP": {"x": 8495.53, "m": 20374.576}, "HUN": {"m": 13.252}, "PRK": {"m": 3.867}, "TZA": {"m": 0.583}, "PRT": {"m": 10.228}, "POL": {"m": 21.367}, "NLD": {"x": 0.0, "m": 6042.199}, "CHN": {"m": 6845.7}, "HKG": {"x": 17.135, "m": 1982.387}, "SVR": {"m": 1.584}, "FRA": {"x": 0.0, "m": 1128.687}, "UNS": {"x": 5.942, "m": 1990.237}, "SER": {"m": 5.572}, "BLX": {"m": 393.335}, "ESP": {"m": 28.842}, "IRQ": {"m": 6.875}, "DNK": {"m": 644.295}, "PAK": {"m": 46.15}, "AUS": {"x": 0.0, "m": 2752.921}, "MMR": {"m": 6.224}, "AUT": {"m": 130.662}, "IRN": {"m": 3.473}, "RUS": {"m": 32.209}, "FIN": {"m": 1.721}, "THA": {"x": 5782.921, "m": 2417.832}, "NZL": {"x": 0.0, "m": 332.417}, "KEN": {"m": 1.774}, "CXR": {"m": 2.422}, "MAR": {"m": 0.715}, "JPN": {"x": 263155.221, "m": 31128.884}, "ZAF": {"m": 6.808}, "PHL": {"x": 0.0, "m": 1272.125}, "ITA": {"m": 1274.954}, "SYR": {"x": 0.0}, "NOR": {"m": 107.276}, "ARG": {"m": 0.717}, "IND": {"x": 0.0, "m": 485.817}, "OAS": {"x": 9646.873, "m": 593.502}, "CZE": {"m": 7.618}, "MEX": {"m": 3.69}, "BRA": {"m": 8.355}, "CUB": {"m": 2.164}}, "1972": {"DZA": {"m": 49.023}, "MLT": {"x": 0.0}, "USA": {"x": 14552.085, "m": 20354.262}, "ISR": {"m": 32.862}, "SWE": {"x": 0.0, "m": 399.54}, "DEU": {"x": 0.0, "m": 3487.387}, "LKA": {"x": 0.0, "m": 69.598}, "IDN": {"x": 0.0, "m": 161.48}, "GBR": {"x": 0.0, "m": 15083.908}, "CAN": {"m": 137.745}, "KOR": {"m": 60.314}, "CHE": {"m": 163.269}, "CYP": {"m": 2.347}, "MYS": {"x": 18928.186, "m": 6289.091}, "SGP": {"x": 9493.362, "m": 16072.699}, "HUN": {"m": 27.931}, "PRK": {"m": 1.923}, "NGA": {"x": 0.0}, "PRT": {"m": 13.292}, "POL": {"m": 7.741}, "NLD": {"x": 0.0, "m": 6149.543}, "CHN": {"x": 0.0, "m": 3112.689}, "HKG": {"x": 16.725, "m": 1704.825}, "FRA": {"x": 0.0, "m": 948.588}, "UNS": {"x": 3.222, "m": 522.217}, "SER": {"m": 1.504}, "BLX": {"m": 394.35}, "ESP": {"m": 34.492}, "IRQ": {"m": 0.67}, "DNK": {"x": 0.0, "m": 782.092}, "PAK": {"m": 14.316}, "ROM": {"m": 0.823}, "AUS": {"x": 3795.165, "m": 3601.898}, "MMR": {"x": 3031.92, "m": 9.467}, "AUT": {"m": 103.013}, "IRN": {"x": 0.0, "m": 2.184}, "RUS": {"m": 48.04}, "SVR": {"m": 0.715}, "THA": {"x": 10169.062, "m": 1989.263}, "NZL": {"x": 2058.31, "m": 271.938}, "MAR": {"m": 0.516}, "JPN": {"x": 91466.927, "m": 21297.668}, "PHL": {"x": 7030.585, "m": 530.257}, "OMN": {"x": 0.0}, "ITA": {"x": 0.0, "m": 594.003}, "NOR": {"m": 162.979}, "ARG": {"m": 3.914}, "IND": {"m": 237.197}, "OAS": {"x": 6038.449, "m": 861.804}, "BHS": {"m": 1.845}, "CZE": {"m": 2.008}, "MEX": {"m": 1.635}, "BRA": {"m": 2.368}, "CUB": {"m": 0.59}}, "1971": {"USA": {"x": 0.0, "m": 35287.632}, "ISR": {"m": 26.185}, "SWE": {"m": 203.623}, "DEU": {"m": 3799.431}, "LKA": {"x": 0.0, "m": 47.039}, "IDN": {"x": 0.0, "m": 132.326}, "GBR": {"x": 0.917, "m": 21967.02}, "CAN": {"m": 39.289}, "KOR": {"m": 32.974}, "CHE": {"x": 0.0, "m": 315.474}, "CYP": {"m": 1.849}, "MYS": {"x": 99578.203, "m": 5184.952}, "SGP": {"x": 190.201, "m": 13775.44}, "HUN": {"m": 2.788}, "PRK": {"m": 0.534}, "PRT": {"m": 6.549}, "POL": {"m": 4.983}, "KHM": {"m": 3.029}, "CHN": {"m": 2501.076}, "HKG": {"x": 14.918, "m": 2682.564}, "SAU": {"m": 27.355}, "NLD": {"x": 0.0, "m": 5899.476}, "FRA": {"x": 0.0, "m": 1232.147}, "UNS": {"x": 3.726, "m": 1598.734}, "BLX": {"m": 225.296}, "AUT": {"m": 129.374}, "ESP": {"m": 36.763}, "IRQ": {"m": 2.751}, "DNK": {"m": 930.015}, "PAK": {"m": 15.792}, "AUS": {"x": 0.0, "m": 3206.653}, "MMR": {"m": 12.257}, "CUB": {"m": 0.725}, "RUS": {"m": 46.742}, "FIN": {"m": 11.452}, "THA": {"x": 0.0, "m": 1668.331}, "NZL": {"m": 197.965}, "JPN": {"x": 0.0, "m": 44687.336}, "PHL": {"x": 1631.749, "m": 340.627}, "OMN": {"x": 0.0}, "ITA": {"x": 0.0, "m": 1045.178}, "NOR": {"m": 19.588}, "ARG": {"m": 1.28}, "IND": {"x": 0.0, "m": 190.216}, "OAS": {"x": 58.8, "m": 671.306}, "MEX": {"m": 2.109}, "BRA": {"m": 0.561}, "CZE": {"m": 6.421}}, "1970": {"USA": {"x": 0.0, "m": 16917.08}, "ISR": {"m": 18.104}, "SWE": {"m": 218.134}, "DEU": {"x": 0.0, "m": 1455.653}, "PER": {"x": 0.0, "m": 0.853}, "LKA": {"x": 0.0, "m": 51.934}, "IDN": {"x": 0.0, "m": 153.646}, "BGR": {"m": 0.773}, "GBR": {"x": 0.999, "m": 14103.841}, "CAN": {"m": 29.983}, "KOR": {"m": 22.254}, "CHE": {"m": 64.797}, "CYP": {"m": 1.608}, "MYS": {"x": 91932.872, "m": 5663.167}, "SGP": {"x": 192.208, "m": 13927.469}, "HUN": {"m": 1.657}, "PRK": {"m": 1.238}, "PRT": {"m": 7.214}, "POL": {"m": 7.301}, "KHM": {"m": 4.14}, "CHN": {"m": 2775.143}, "HKG": {"x": 41.23, "m": 2368.06}, "NLD": {"x": 0.653, "m": 1778.71}, "CUW": {"m": 0.538}, "FRA": {"m": 810.941}, "UNS": {"x": 6.002, "m": 1547.785}, "BLX": {"m": 121.438}, "ESP": {"m": 35.285}, "IRQ": {"m": 1.699}, "DNK": {"m": 568.697}, "PAK": {"x": 0.0, "m": 8.324}, "ROM": {"m": 1.564}, "AUS": {"m": 3057.205}, "MMR": {"x": 0.0, "m": 83.971}, "GRC": {"m": 73.133}, "RUS": {"m": 27.367}, "FIN": {"m": 8.816}, "THA": {"m": 1957.963}, "NZL": {"x": 0.0, "m": 98.602}, "MAR": {"m": 2.302}, "SVR": {"m": 0.758}, "JPN": {"x": 0.0, "m": 12891.423}, "ZAF": {"m": 16.828}, "PHL": {"x": 0.0, "m": 27.361}, "ITA": {"x": 0.0, "m": 379.413}, "CUB": {"m": 0.798}, "ARG": {"m": 11.449}, "IND": {"m": 305.706}, "OAS": {"x": 0.0, "m": 699.659}, "CZE": {"m": 39.073}, "MEX": {"m": 1.683}, "NOR": {"m": 35.801}, "AUT": {"m": 168.724}}, "2002": {"AGO": {"m": 1.208}, "QAT": {"x": 0.0, "m": 15.249}, "EGY": {"x": 0.0, "m": 142.008}, "BGD": {"x": 0.0, "m": 30.241}, "OAS": {"x": 18.213, "m": 18579.71}, "PAK": {"x": 0.0, "m": 1166.067}, "PAN": {"x": 5.152}, "JOR": {"x": 0.0, "m": 11.762}, "LBY": {"x": 0.0}, "MYS": {"x": 1257.824, "m": 224640.176}, "PRK": {"x": 0.775, "m": 147.294}, "PRT": {"m": 9.249}, "KHM": {"x": 0.0, "m": 3.766}, "HKG": {"x": 382.321, "m": 61368.896}, "SAU": {"x": 0.0, "m": 807.712}, "LBN": {"x": 6.665, "m": 126.571}, "CHE": {"x": 0.0, "m": 2284.41}, "CHL": {"m": 153.549}, "CHN": {"x": 224522.763, "m": 57871.212}, "LAO": {"x": 3.578, "m": 0.593}, "FIN": {"x": 0.0, "m": 252.475}, "THA": {"x": 472023.83, "m": 54708.708}, "SYC": {"m": 3.679}, "NPL": {"x": 0.0, "m": 221.897}, "MAR": {"x": 0.0, "m": 31.087}, "PHL": {"x": 21720.305, "m": 2443.012}, "ZAF": {"m": 244.047}, "SYR": {"x": 0.0, "m": 18.238}, "MAC": {"x": 0.0, "m": 36.184}, "NGA": {"x": 0.0, "m": 17.6}, "BEL": {"x": 0.0, "m": 8254.185}, "DEU": {"x": 17.699, "m": 43032.58}, "LKA": {"x": 0.0, "m": 131.365}, "GBR": {"x": 1071.535, "m": 95314.72}, "ITA": {"x": 29.134, "m": 11240.054}, "ROM": {"m": 403.743}, "HUN": {"m": 28.108}, "NLD": {"x": 20.782, "m": 7895.045}, "BLZ": {"m": 49.944}, "AFG": {"x": 0.0, "m": 24.845}, "VGB": {"m": 3.007}, "GRC": {"x": 0.0, "m": 8.449}, "BRB": {"m": 0.686}, "IND": {"x": 10.701, "m": 7249.473}, "VNM": {"x": 0.0, "m": 831.733}, "NOR": {"x": 0.0, "m": 1981.519}, "CZE": {"m": 69.762}, "FJI": {"m": 4.673}, "MLT": {"m": 1.918}, "MUS": {"m": 1.531}, "LUX": {"m": 196.247}, "ISR": {"m": 5.554}, "PER": {"m": 3.269}, "IDN": {"x": 29811.712, "m": 36696.12}, "COL": {"m": 1.222}, "SER": {"m": 3.339}, "BWA": {"m": 8.542}, "ECU": {"m": 21.371}, "FRA": {"x": 48.452, "m": 15864.728}, "UNS": {"x": 6.272, "m": 2825.179}, "ZMB": {"x": 0.0}, "GTM": {"m": 1.712}, "DNK": {"x": 0.0, "m": 1359.758}, "AUS": {"x": 312037.435, "m": 39014.948}, "AUT": {"x": 4.341, "m": 302.219}, "VEN": {"x": 0.0}, "KEN": {"m": 22.01}, "TUR": {"x": 131.618, "m": 107.132}, "OMN": {"x": 0.91, "m": 89.282}, "MMR": {"x": 0.0, "m": 125.987}, "TUN": {"m": 8.519}, "RUS": {"m": 73.379}, "MEX": {"x": 68.488, "m": 70.55}, "BRA": {"m": 446.349}, "CIV": {"x": 4.436}, "USA": {"x": 269660.872, "m": 276732.416}, "SWE": {"x": 0.0, "m": 2581.079}, "UKR": {"m": 10.821}, "SWZ": {"m": 3.178}, "CAN": {"x": 1699.78, "m": 1705.86}, "USP": {"m": 0.698}, "KOR": {"x": 417879.198, "m": 29882.758}, "CYP": {"m": 18.4}, "SGP": {"x": 107720.292, "m": 271589.664}, "POL": {"m": 132.611}, "KWT": {"x": 0.0}, "ESP": {"x": 10001.81, "m": 3386.966}, "IRL": {"m": 1070.733}, "IRN": {"x": 0.0, "m": 662.588}, "NZL": {"x": 58453.068, "m": 2375.727}, "JPN": {"x": 1438297.593, "m": 205755.76}, "ARE": {"x": 0.0, "m": 2906.803}, "ARG": {"m": 520.631}, "BHR": {"x": 0.0, "m": 7.925}, "UGA": {"m": 1.919}, "PNG": {"x": 0.0, "m": 3.946}}, "2003": {"DZA": {"m": 14.781}, "QAT": {"x": 81.482, "m": 5.092}, "EGY": {"x": 0.0, "m": 98.351}, "BGD": {"x": 0.0, "m": 70.549}, "OAS": {"x": 17.663, "m": 18581.992}, "GHA": {"x": 0.0}, "PAK": {"x": 0.0, "m": 366.414}, "PAN": {"m": 42.878}, "JOR": {"m": 3.626}, "LBY": {"x": 0.0}, "MYS": {"x": 12698.8, "m": 251598.448}, "PRK": {"x": 30.689, "m": 75.612}, "TZA": {"x": 0.0, "m": 69.057}, "PRT": {"m": 9.24}, "KHM": {"x": 0.0, "m": 136.24}, "HKG": {"x": 452.132, "m": 81589.784}, "SAU": {"x": 0.0, "m": 1259.871}, "LBN": {"m": 7.955}, "CHE": {"x": 1.082, "m": 2658.449}, "CHL": {"m": 97.738}, "CHN": {"x": 276040.437, "m": 60443.732}, "LAO": {"m": 1.335}, "FIN": {"m": 504.326}, "URY": {"m": 5.459}, "THA": {"x": 389513.714, "m": 50416.616}, "SYC": {"m": 1.286}, "NPL": {"x": 0.0, "m": 3.152}, "MAR": {"m": 27.799}, "PHL": {"x": 0.0, "m": 2563.25}, "ZAF": {"m": 402.123}, "SYR": {"x": 0.0, "m": 26.355}, "MLT": {"m": 0.965}, "NGA": {"x": 0.0, "m": 0.899}, "BEL": {"x": 0.0, "m": 4671.017}, "DEU": {"x": 6.89, "m": 40066.42}, "LKA": {"x": 0.0, "m": 197.142}, "GBR": {"x": 1332.853, "m": 45613.984}, "MWI": {"m": 2.893}, "ITA": {"x": 0.0, "m": 8610.501}, "ROM": {"x": 0.0}, "HUN": {"m": 20.147}, "NLD": {"x": 5.02, "m": 5851.031}, "BLZ": {"m": 49.174}, "AFG": {"x": 0.0, "m": 53.657}, "GRC": {"m": 4.108}, "GRL": {"m": 0.796}, "IND": {"x": 83620.338, "m": 6817.194}, "VNM": {"x": 8.37, "m": 847.954}, "NOR": {"x": 0.0, "m": 1277.87}, "CZE": {"m": 15.36}, "HND": {"m": 14.218}, "MUS": {"x": 0.0}, "DOM": {"m": 3.122}, "ISR": {"m": 17.382}, "PER": {"m": 24.178}, "IDN": {"x": 104883.714, "m": 33002.872}, "COD": {"m": 83.093}, "ISL": {"m": 0.656}, "SER": {"x": 0.0}, "BWA": {"m": 0.541}, "ECU": {"m": 54.789}, "FRA": {"x": 0.0, "m": 20745.606}, "UNS": {"x": 7.443, "m": 3435.441}, "GTM": {"m": 1.634}, "DNK": {"x": 4.054, "m": 574.665}, "AUS": {"x": 344958.453, "m": 36966.12}, "AUT": {"x": 22.53, "m": 388.139}, "VEN": {"x": 0.0}, "KEN": {"x": 0.0}, "TUR": {"m": 88.98}, "OMN": {"x": 0.0, "m": 95.273}, "MMR": {"x": 2.148, "m": 122.061}, "RUS": {"x": 0.0, "m": 1.935}, "MEX": {"x": 175.192, "m": 123.46}, "BRA": {"m": 190.624}, "CIV": {"x": 0.0}, "USA": {"x": 308458.084, "m": 143017.904}, "SWE": {"x": 0.0, "m": 1668.416}, "UKR": {"m": 10.233}, "SWZ": {"m": 3.736}, "CAN": {"x": 2193.83, "m": 2966.571}, "KOR": {"x": 463699.091, "m": 29242.416}, "CYP": {"m": 75.281}, "SGP": {"x": 67873.92, "m": 250108.016}, "POL": {"m": 10.752}, "KWT": {"x": 0.0}, "ESP": {"x": 0.0, "m": 3381.783}, "IRQ": {"x": 0.0}, "IRL": {"x": 0.0, "m": 1495.009}, "IRN": {"m": 523.029}, "NZL": {"x": 96464.088, "m": 1925.593}, "JPN": {"x": 1696406.466, "m": 124295.984}, "NCL": {"x": 0.0}, "ARE": {"x": 0.0, "m": 2733.844}, "ARG": {"m": 616.819}, "BHR": {"x": 0.0, "m": 6.148}, "PNG": {"m": 0.677}}, "2001": {"DZA": {"x": 0.0}, "EGY": {"x": 0.0, "m": 419.189}, "BGD": {"x": 0.0, "m": 3.188}, "BGR": {"m": 0.653}, "BOL": {"m": 0.621}, "PAK": {"x": 0.0, "m": 321.121}, "PAN": {"x": 0.782}, "JOR": {"m": 27.731}, "LBR": {"x": 0.0}, "MYS": {"x": 6353.316, "m": 228879.744}, "PRK": {"x": 3.73, "m": 90.533}, "TZA": {"m": 1.76}, "PRT": {"m": 64.194}, "KHM": {"m": 22.783}, "HKG": {"x": 1764.813, "m": 56215.504}, "SAU": {"x": 0.0, "m": 238.32}, "CHE": {"x": 0.0, "m": 2292.909}, "CHL": {"m": 69.553}, "CHN": {"x": 144279.913, "m": 36293.888}, "JAM": {"m": 1.19}, "FIN": {"x": 0.0, "m": 272.093}, "THA": {"x": 414237.024, "m": 47073.296}, "NPL": {"x": 0.0, "m": 169.748}, "LAO": {"x": 0.0}, "PHL": {"x": 0.0, "m": 3322.963}, "ZAF": {"m": 475.286}, "SYR": {"x": 0.0, "m": 15.071}, "MAC": {"x": 0.0}, "MLT": {"m": 2.667}, "OAS": {"x": 1.305, "m": 20412.732}, "COD": {"m": 4.608}, "NGA": {"x": 0.0}, "BEL": {"x": 0.0, "m": 2052.018}, "DEU": {"x": 24.577, "m": 38017.896}, "LKA": {"x": 0.537, "m": 166.977}, "GBR": {"x": 463.403, "m": 44493.316}, "MWI": {"m": 0.511}, "ITA": {"x": 0.0, "m": 49993.604}, "ROM": {"m": 36.502}, "HUN": {"m": 27.109}, "NLD": {"x": 315.849, "m": 9694.9}, "BLZ": {"m": 11.683}, "AFG": {"m": 46.79}, "GRC": {"m": 20.115}, "GRL": {"m": 5.542}, "IND": {"x": 50105.708, "m": 4333.783}, "VNM": {"x": 0.0, "m": 657.907}, "NOR": {"x": 0.0, "m": 597.601}, "CZE": {"m": 26.612}, "ATG": {"m": 535.229}, "HND": {"m": 21.452}, "MUS": {"x": 0.0, "m": 5.409}, "LUX": {"m": 25.599}, "ISR": {"m": 27.279}, "PER": {"m": 10.731}, "IDN": {"x": 39874.874, "m": 25649.968}, "SUR": {"m": 14.588}, "ISL": {"x": 3.563, "m": 5.299}, "SER": {"m": 1.342}, "BWA": {"m": 21.507}, "FRA": {"x": 4.584, "m": 18857.916}, "UNS": {"x": 4.016, "m": 2737.128}, "ZMB": {"x": 0.0}, "GTM": {"m": 1.382}, "DNK": {"x": 0.0, "m": 964.163}, "AUS": {"x": 190885.675, "m": 38787.304}, "AUT": {"x": 0.0, "m": 429.8}, "VEN": {"m": 62.113}, "KEN": {"m": 1.974}, "TUR": {"m": 209.273}, "OMN": {"x": 0.0, "m": 272.219}, "MMR": {"x": 0.0, "m": 22.078}, "TUN": {"m": 7.516}, "RUS": {"x": 0.0, "m": 2.387}, "MEX": {"x": 0.0, "m": 68.754}, "BRA": {"x": 0.0, "m": 121.727}, "USA": {"x": 254175.635, "m": 102126.016}, "SWE": {"x": 0.0, "m": 1865.515}, "UKR": {"m": 5.347}, "SWZ": {"m": 8.237}, "CAN": {"x": 1297.669, "m": 1188.152}, "USP": {"m": 85.502}, "KOR": {"x": 416035.54, "m": 16528.33}, "CYP": {"m": 21.681}, "SGP": {"x": 127441.168, "m": 261853.488}, "POL": {"m": 114.461}, "KWT": {"x": 0.0}, "ARE": {"x": 141.533, "m": 2698.263}, "ESP": {"x": 0.0, "m": 1701.709}, "IRL": {"x": 28.567, "m": 599.611}, "IRN": {"m": 426.56}, "NZL": {"x": 29118.245, "m": 2803.914}, "JPN": {"x": 1612085.537, "m": 71573.816}, "PNG": {"x": 0.0, "m": 16.663}, "ARG": {"m": 905.824}, "BHR": {"m": 0.642}, "UGA": {"m": 15.185}, "NRU": {"x": 0.0}, "CUB": {"m": 3.885}}, "2006": {"AGO": {"m": 0.209}, "QAT": {"x": 51.607, "m": 7.693}, "EGY": {"x": 150.604, "m": 71.727}, "BGD": {"x": 19.494, "m": 63.921}, "BGR": {"m": 0.718}, "OAS": {"x": 132.955, "m": 27553.955}, "GHA": {"x": 7.48, "m": 0.122}, "PAK": {"x": 135.635, "m": 541.74}, "PAN": {"m": 2.715}, "JOR": {"x": 20.981, "m": 28.933}, "LBY": {"x": 8.179}, "MYS": {"x": 40157.058, "m": 362530.216}, "PRK": {"x": 285.085, "m": 72.878}, "TZA": {"x": 1.098, "m": 1.324}, "BWA": {"m": 0.02}, "KHM": {"x": 57.615, "m": 44.611}, "HKG": {"x": 1550.684, "m": 55406.801}, "SAU": {"x": 127.324, "m": 664.125}, "LBN": {"m": 185.447}, "CHE": {"x": 12.62, "m": 4287.442}, "CHL": {"m": 104.668}, "CHN": {"x": 176810.998, "m": 131736.539}, "JAM": {"m": 0.453}, "FIN": {"m": 2796.294}, "THA": {"x": 144035.87, "m": 92839.035}, "SYC": {"m": 0.16}, "NPL": {"x": 292.974, "m": 146.211}, "MAR": {"m": 0.073}, "YEM": {"m": 22.372}, "PHL": {"x": 672.258, "m": 5640.473}, "ZAF": {"m": 1173.72}, "SYR": {"x": 17.969, "m": 10.855}, "MAC": {"m": 2.059}, "NGA": {"x": 2212.312, "m": 27.257}, "BEL": {"x": 179.316, "m": 5630.455}, "DEU": {"x": 3849.129, "m": 39762.545}, "LKA": {"x": 125.982, "m": 320.244}, "GBR": {"x": 10057.238, "m": 46065.199}, "MWI": {"m": 39.874}, "ITA": {"x": 237.211, "m": 36139.626}, "CMR": {"m": 0.543}, "ROM": {"x": 0.187, "m": 6.694}, "HUN": {"x": 4.118, "m": 119.135}, "NLD": {"x": 2369.598, "m": 14829.83}, "BMU": {"m": 0.793}, "MNG": {"x": 1.607, "m": 0.055}, "BLZ": {"m": 118.367}, "AFG": {"m": 17.682}, "BDI": {"m": 1.41}, "GRC": {"m": 205.732}, "GRL": {"m": 0.006}, "IND": {"x": 376263.92, "m": 8920.458}, "VNM": {"x": 74.659, "m": 1501.037}, "NOR": {"x": 290.916, "m": 3594.543}, "CZE": {"x": 0.042, "m": 6963.021}, "FJI": {"x": 12.988, "m": 0.006}, "MLT": {"m": 14.871}, "MUS": {"x": 152.737}, "DOM": {"m": 4.381}, "LUX": {"m": 47.715}, "ISR": {"x": 0.491, "m": 46.988}, "PER": {"m": 8.965}, "IDN": {"x": 1515746.731, "m": 46506.847}, "SUR": {"m": 1.953}, "COG": {"m": 0.807}, "ISL": {"m": 6.728}, "COL": {"x": 1.156, "m": 2.276}, "SER": {"m": 0.159}, "PRT": {"m": 80.898}, "MDG": {"m": 1.377}, "ECU": {"m": 15.188}, "MDV": {"m": 0.03}, "ASM": {"m": 0.149}, "FRA": {"x": 992.706, "m": 16998.197}, "UNS": {"x": 75.279, "m": 3741.772}, "WSM": {"m": 0.042}, "GTM": {"m": 6.599}, "DNK": {"x": 224.572, "m": 1283.235}, "AUS": {"x": 933042.689, "m": 33078.838}, "AUT": {"x": 139.235, "m": 514.178}, "VEN": {"m": 3.446}, "LAO": {"x": 116.577, "m": 8.481}, "TUR": {"x": 9.291, "m": 255.564}, "ALB": {"m": 2.861}, "OMN": {"x": 430.446, "m": 119.375}, "MMR": {"x": 37.714, "m": 2580.874}, "TUN": {"x": 7.795}, "RUS": {"x": 3570.737, "m": 26.866}, "MEX": {"m": 430.871}, "BRA": {"x": 0.235, "m": 648.758}, "USA": {"x": 513712.857, "m": 151388.164}, "SWE": {"x": 0.988, "m": 2892.381}, "UKR": {"m": 17.935}, "SWZ": {"m": 4.535}, "CAN": {"x": 1381.883, "m": 13903.769}, "KOR": {"x": 1150016.333, "m": 27629.435}, "CYP": {"x": 177.3, "m": 186.769}, "SGP": {"x": 190989.729, "m": 291046.333}, "POL": {"x": 0.715, "m": 136.364}, "KWT": {"x": 5.159, "m": 0.255}, "ESP": {"x": 17.045, "m": 4050.989}, "IRL": {"x": 2.606, "m": 1633.075}, "IRN": {"x": 45.013, "m": 146.909}, "SLE": {"m": 0.225}, "SDN": {"m": 0.171}, "NZL": {"x": 226386.236, "m": 7999.284}, "JPN": {"x": 2337531.112, "m": 214648.217}, "ARE": {"x": 850.701, "m": 3284.257}, "ARG": {"x": 185.396, "m": 547.99}, "BHS": {"m": 0.013}, "BHR": {"x": 15.881, "m": 5.966}, "PNG": {"x": 7.615, "m": 0.321}, "CUB": {"m": 0.485}}, "2007": {"DZA": {"x": 15.395, "m": 18.745}, "QAT": {"x": 237.691, "m": 8.371}, "EGY": {"x": 129.295, "m": 253.09}, "BGD": {"x": 4.834, "m": 57.368}, "BGR": {"m": 3.327}, "BOL": {"m": 352.233}, "GHA": {"m": 6.25}, "PAK": {"x": 148.138, "m": 382.002}, "PAN": {"x": 15.031, "m": 1.05}, "JOR": {"x": 7.179, "m": 20.024}, "LBY": {"x": 58.742, "m": 0.005}, "MYS": {"x": 61254.226, "m": 397289.305}, "PRK": {"x": 123.357, "m": 16.839}, "TZA": {"x": 47.213, "m": 20.858}, "PRT": {"x": 1.009, "m": 4457.861}, "KHM": {"x": 8.963, "m": 0.219}, "TTO": {"m": 0.025}, "HKG": {"x": 906.953, "m": 52111.554}, "SAU": {"x": 558.567, "m": 1508.671}, "LBN": {"m": 229.99}, "CHE": {"x": 175.39, "m": 5570.964}, "CHL": {"m": 130.716}, "CHN": {"x": 202030.03, "m": 157823.862}, "LAO": {"x": 34.251, "m": 6.567}, "GIN": {"m": 2.1}, "FIN": {"x": 0.595, "m": 3725.043}, "URY": {"m": 0.559}, "THA": {"x": 106361.543, "m": 103765.488}, "NPL": {"x": 106.66, "m": 205.749}, "CXR": {"x": 0.079}, "MAR": {"x": 3.454, "m": 2.008}, "YEM": {"x": 121.959, "m": 65.286}, "PHL": {"x": 946.511, "m": 6565.364}, "ZAF": {"m": 1470.135}, "SYR": {"x": 5.459, "m": 19.288}, "MAC": {"x": 3.994, "m": 10.67}, "OAS": {"x": 385.978, "m": 42203.362}, "NGA": {"x": 209.852, "m": 2.831}, "BEL": {"x": 162.79, "m": 11690.387}, "DEU": {"x": 4398.196, "m": 58699.632}, "GUM": {"m": 1.019}, "LKA": {"x": 12.212, "m": 207.448}, "GBR": {"x": 8589.466, "m": 77783.769}, "MWI": {"m": 91.606}, "ITA": {"x": 35.375, "m": 16964.238}, "CMR": {"m": 0.108}, "ROM": {"m": 620.328}, "HUN": {"x": 3.875, "m": 290.938}, "BUN": {"x": 2.614}, "NLD": {"x": 4092.675, "m": 22022.12}, "MNG": {"x": 1.282, "m": 0.096}, "BLZ": {"m": 170.447}, "AFG": {"x": 21.617, "m": 47.562}, "GRC": {"x": 8.913, "m": 662.212}, "BRB": {"m": 0.01}, "IND": {"x": 182180.16, "m": 14536.463}, "VNM": {"x": 170.968, "m": 2454.67}, "NOR": {"x": 608.252, "m": 4054.976}, "FJI": {"x": 96.998}, "HND": {"m": 0.254}, "MUS": {"x": 317.91, "m": 1.149}, "DOM": {"m": 1.684}, "LUX": {"m": 0.946}, "ISR": {"x": 3.229, "m": 37.28}, "PER": {"m": 12.327}, "IDN": {"x": 1858973.356, "m": 61781.152}, "COG": {"m": 7.313}, "ISL": {"m": 1.021}, "COL": {"x": 7.816, "m": 15.162}, "SER": {"m": 410.18}, "MDG": {"m": 2.895}, "ECU": {"m": 9.089}, "CUW": {"x": 1.154}, "FRA": {"x": 459.204, "m": 22709.737}, "UNS": {"x": 99.43, "m": 6101.873}, "WSM": {"x": 54.465, "m": 0.05}, "GTM": {"m": 4.855}, "DNK": {"x": 35.658, "m": 2983.246}, "AUS": {"x": 1054539.034, "m": 34798.113}, "AUT": {"x": 0.845, "m": 725.908}, "VEN": {"m": 5.441}, "KEN": {"x": 0.405}, "TUR": {"x": 5.151, "m": 340.667}, "ALB": {"x": 4.944, "m": 0.171}, "OMN": {"x": 401.369, "m": 46.136}, "MMR": {"x": 54.39, "m": 1969.414}, "TUN": {"m": 4.789}, "RUS": {"x": 335.349, "m": 41.712}, "MEX": {"x": 309.623, "m": 235.235}, "BRA": {"x": 0.712, "m": 2627.99}, "USA": {"x": 387742.997, "m": 267928.615}, "SWE": {"x": 24.171, "m": 3974.443}, "UKR": {"m": 20.549}, "SWZ": {"m": 15.588}, "CAN": {"x": 1599.491, "m": 5264.588}, "KOR": {"x": 933002.763, "m": 34078.24}, "CYP": {"x": 0.047, "m": 264.407}, "SGP": {"x": 132952.223, "m": 471449.741}, "POL": {"x": 48.491, "m": 63.56}, "KWT": {"x": 57.188, "m": 12.609}, "ESP": {"x": 13.523, "m": 3082.954}, "IRQ": {"x": 0.214, "m": 0.009}, "IRL": {"m": 1516.446}, "IRN": {"x": 3.494, "m": 264.886}, "ABW": {"m": 15.379}, "NZL": {"x": 173449.762, "m": 7415.08}, "JPN": {"x": 2573632.328, "m": 177939.006}, "ARE": {"x": 822.264, "m": 3634.909}, "ARG": {"m": 454.334}, "SDN": {"m": 0.131}, "BHR": {"x": 4.749, "m": 24.1}, "TKL": {"m": 0.226}, "PNG": {"x": 33.064, "m": 0.173}}, "2004": {"AGO": {"m": 3.472}, "DZA": {"x": 1.962}, "EGY": {"x": 195.33, "m": 74.729}, "BGD": {"x": 40.046, "m": 3.752}, "QAT": {"x": 26.321, "m": 1.502}, "BGR": {"m": 0.906}, "OAS": {"x": 4188.828, "m": 20949.65}, "GHA": {"x": 12.984, "m": 0.257}, "PAK": {"x": 44.06, "m": 402.606}, "PAN": {"m": 39.57}, "JOR": {"x": 4.229, "m": 56.726}, "LBY": {"x": 0.067, "m": 0.009}, "MYS": {"x": 70778.18, "m": 287349.351}, "PRK": {"x": 38.848, "m": 125.035}, "TZA": {"m": 72.64}, "PRT": {"m": 44.236}, "KHM": {"x": 7.745, "m": 2.714}, "HKG": {"x": 3064.404, "m": 73162.74}, "SAU": {"x": 98.075, "m": 1036.274}, "LBN": {"m": 250.909}, "CHE": {"x": 38.324, "m": 5067.143}, "CHL": {"m": 166.943}, "CHN": {"x": 205349.591, "m": 88292.045}, "FIN": {"x": 0.152, "m": 400.427}, "THA": {"x": 349156.831, "m": 65922.154}, "SYC": {"m": 8.177}, "NPL": {"x": 850.123, "m": 30.245}, "LAO": {"x": 32.641, "m": 7.6}, "YEM": {"x": 2.247, "m": 0.056}, "PHL": {"x": 774.84, "m": 4141.049}, "ZAF": {"m": 1413.406}, "SYR": {"m": 4.526}, "MAC": {"m": 1.557}, "MLT": {"m": 0.106}, "NGA": {"x": 269.83, "m": 23.927}, "BEL": {"x": 81.98, "m": 6624.585}, "DEU": {"x": 4457.456, "m": 60967.809}, "LKA": {"x": 78.059, "m": 161.104}, "GBR": {"x": 21331.313, "m": 53255.538}, "MWI": {"m": 31.575}, "ITA": {"x": 493.133, "m": 11406.074}, "ROM": {"m": 5.639}, "HUN": {"m": 45.731}, "NLD": {"x": 2661.907, "m": 13270.102}, "BMU": {"m": 0.235}, "BLZ": {"m": 126.838}, "AFG": {"m": 25.362}, "BDI": {"m": 0.15}, "GRC": {"x": 6.377, "m": 15.725}, "GRL": {"m": 24.649}, "BRB": {"m": 0.82}, "IND": {"x": 288813.513, "m": 8019.967}, "VNM": {"x": 195.47, "m": 718.698}, "NOR": {"x": 353.886, "m": 1148.613}, "CZE": {"m": 55.506}, "FJI": {"x": 12.061, "m": 0.045}, "HND": {"m": 0.01}, "MUS": {"x": 258.573, "m": 0.011}, "DOM": {"m": 0.033}, "LUX": {"m": 0.473}, "ISR": {"m": 17.655}, "PER": {"m": 14.131}, "IDN": {"x": 316672.402, "m": 31158.689}, "COD": {"m": 2.53}, "ISL": {"m": 1.292}, "UMI": {"m": 0.014}, "COL": {"m": 0.546}, "SER": {"x": 0.013}, "MDG": {"m": 0.939}, "ECU": {"x": 1.074, "m": 48.142}, "CUW": {"x": 17.541}, "FRA": {"x": 1312.948, "m": 13322.383}, "UNS": {"x": 663.134, "m": 2597.609}, "GTM": {"m": 6.312}, "DNK": {"x": 414.84, "m": 1123.211}, "AUS": {"x": 594159.329, "m": 39435.879}, "AUT": {"x": 10.78, "m": 1182.617}, "VEN": {"x": 7.733, "m": 1.169}, "KEN": {"m": 93.915}, "TUR": {"x": 0.066, "m": 124.738}, "OMN": {"x": 406.065, "m": 178.331}, "MMR": {"x": 83.548, "m": 157.907}, "TUN": {"m": 1.794}, "RUS": {"x": 11.551, "m": 43.468}, "MEX": {"x": 8.824, "m": 802.584}, "BRA": {"m": 375.04}, "USA": {"x": 349879.09, "m": 167467.78}, "SWE": {"x": 112.885, "m": 3993.424}, "UKR": {"m": 9.497}, "SWZ": {"m": 8.504}, "CAN": {"x": 1547.657, "m": 3329.654}, "KOR": {"x": 651416.791, "m": 40215.712}, "CYP": {"m": 77.334}, "SGP": {"x": 132511.896, "m": 261481.763}, "POL": {"m": 73.86}, "KWT": {"x": 6.498, "m": 6.067}, "ESP": {"x": 336.101, "m": 4955.294}, "IRQ": {"x": 0.63, "m": 0.092}, "MLI": {"m": 0.016}, "IRL": {"x": 96.349, "m": 1402.769}, "IRN": {"m": 323.976}, "ABW": {"m": 4.599}, "SLE": {"m": 0.122}, "NZL": {"x": 152146.034, "m": 4193.318}, "JPN": {"x": 1911674.186, "m": 140207.725}, "ARE": {"x": 1811.811, "m": 3081.391}, "ARG": {"m": 444.053}, "BHR": {"m": 6.09}, "UGA": {"x": 23.637, "m": 0.041}, "PNG": {"x": 72.004, "m": 0.677}, "CUB": {"m": 0.024}}, "1976": {"EGY": {"m": 2.895}, "MLT": {"m": 0.583}, "USA": {"x": 141450.305, "m": 62435.16}, "ISR": {"m": 15.795}, "MOZ": {"m": 0.966}, "SWE": {"m": 767.258}, "DEU": {"x": 0.0, "m": 9714.631}, "LKA": {"x": 0.0, "m": 17.691}, "IDN": {"m": 723.111}, "GBR": {"x": 0.0, "m": 37476.216}, "CAN": {"m": 341.086}, "ROM": {"m": 4.812}, "KOR": {"m": 240.938}, "CHE": {"m": 548.337}, "CYP": {"m": 2.163}, "MYS": {"x": 67400.753, "m": 13222.036}, "SGP": {"x": 17416.791, "m": 38894.02}, "HUN": {"m": 59.558}, "PRK": {"m": 90.432}, "NGA": {"x": 0.0}, "PRT": {"m": 35.914}, "POL": {"m": 55.404}, "USP": {"m": 3.532}, "NLD": {"x": 0.0, "m": 7859.629}, "CHN": {"m": 6467.55}, "HKG": {"x": 104.852, "m": 3446.564}, "CUW": {"m": 4.234}, "VNM": {"m": 1.319}, "FRA": {"m": 3068.201}, "UNS": {"x": 2.643, "m": 2412.215}, "SER": {"m": 0.787}, "BLX": {"x": 0.0, "m": 1373.87}, "AUT": {"m": 148.995}, "ESP": {"m": 106.505}, "IRQ": {"m": 5.392}, "CHL": {"m": 2.485}, "DNK": {"m": 1177.261}, "PAK": {"m": 21.25}, "NOR": {"m": 457.824}, "AUS": {"x": 20.512, "m": 4624.524}, "MMR": {"m": 11.229}, "IRL": {"x": 0.0, "m": 12.825}, "CUB": {"m": 0.556}, "IRN": {"x": 0.0, "m": 1.631}, "RUS": {"m": 20.338}, "FIN": {"m": 684.192}, "THA": {"x": 0.0, "m": 4595.945}, "NZL": {"x": 0.0, "m": 671.437}, "KEN": {"m": 0.983}, "MAR": {"m": 2.103}, "COD": {"m": 432.205}, "JPN": {"x": 903124.368, "m": 43887.512}, "ZAF": {"x": 109215.728, "m": 10.818}, "PHL": {"x": 1756.902, "m": 1242.276}, "OMN": {"x": 0.0}, "ITA": {"x": 4.402, "m": 1725.221}, "SYR": {"m": 1.023}, "ARE": {"x": 0.0}, "ARG": {"m": 10.727}, "IND": {"m": 591.179}, "OAS": {"x": 46872.928, "m": 2318.357}, "MEX": {"m": 10.622}, "BRA": {"m": 65.913}, "CZE": {"m": 27.175}}}